{
    "published": "2018-05-05",
    "title": "官田區107年度模範母親表揚大會",
    "department": "",
    "url": "https:\/\/www.tainan.gov.tw\/News_Content.aspx?n=40854&s=176882",
    "content": "為慶祝母親節，官田區公所今(5)日上午假官田國中活動中心舉辦107年度模範母親表揚大會，顏區長、農會、市議員、里長、國中小校長及各界代表共同出席與會頒贈匾額，分享喜樂及榮耀。\n今日活動，區公所安排子女牽著模範母親的手走紅毯進場並接受在場每位民眾的熱烈掌聲祝賀。顏區長致詞：「首先祝福在場每一位母親，母親節快樂！溫馨五月天，感恩母愛情！母親將善良的一面發揚光大，為人子女應學習，更應及時行孝。」\n官田區107年度模範母親代表：二鎮里李辜玉秀、官田里陳林秀琴、渡頭里許賴春綢、東庄里陳謝綉蓮、社子里黃高珠 、西庄里陳梁怨、南廍里周鄭貴氣、隆田里胡黃環、湖山里岩陳月霞、隆本里廖嘉羚、拔林里方陳美麗、大崎里陳余美玉。\n大崎里模範母親陳余美玉女士昨(4)日接受台南市政府慈暉媽媽表揚；陳余女士與先生育有8名女兒，因重男輕女觀念深植早期傳統農村社會，備受歧視並遭受不公平待遇；20幾年前丈夫病倒，為了照顧丈夫、年邁的婆婆及女兒，母代父職，扛起家計重責大任，充分展現母愛的韌性，而今8名女兒成就非凡，更深受母親樂於助人的精神影響，樂善好施。\n表揚過程由二鎮社區媽媽舞蹈揭開序幕及陳敏群先生薩克斯風演奏；本所特別安排奉茶儀式由子女為母親奉茶並獻上擁抱表達對母親的感恩，另播放模範母親家庭子女的感言影片，場面溫馨感人。",
    "tags": ""
}