{
    "published": "2018-05-18",
    "title": "臺南市政府消防局「第五救災救護大隊關廟分隊新建工程」落成啟用暨捐車典禮",
    "department": "",
    "url": "https:\/\/www.tainan.gov.tw\/News_Content.aspx?n=40854&s=188583",
    "content": "消防局本日上午舉辦第五救災救護大隊關廟分隊廳舍落成啟用典禮暨災情勘查車捐贈儀式，由副市長張政源主持，邀請各界民意代表、消防及義消單位等蒞臨指導，原興建於民國75年已具30多年歷史的關廟消防分隊，歷經各種規模地震，耐震能力經評估已不符合需求，為提升關廟與龍崎地區救災救護效率，決定原址重建，將關廟地方特色（如關廟三寶、藤編工藝、傳統廟宇等語彙）融入關廟分隊廳舍的建築規劃意象，做為關廟新地標，基地位於182市道進入關廟區的樞紐位置，對於關廟入口意象扮演舉足輕重的角色。且北側關廟國中已進行全校重建規劃，可與本廳舍相互搭配，成為關廟之門。本案興建經費在局長李明峯努力及市議會的支持下，分期分年編列新臺幣3,640萬元，委託「解構聯合建築師事務所」規劃設計監造，並由「繁華工程有限公司」承包，於105年9月10日開工，106年12月21日竣工，107年3月1日驗收合格，順利完成。新廳舍為地上4層樓鋼筋混凝土之建築，總樓地板面積為1,272平方公尺，整體架構以執勤救災空間為核心，內部空間規劃1樓為值勤室、救災器材室、油料室、車庫；2樓為辦公室、備勤室；3樓為休閒室、備勤室；4樓為會議室，並可容納6部各式消救車輛，有效提升空間使用效率，啟用後可強化關廟及龍崎地區之防救災需求，提供市民更優質之公共安全守護。另由創辦人陳慶飛所創建龍崎區文衡殿，奉獻社會不遺餘力，感念關廟消防分隊處於關廟及龍崎地區幅員廣闊，缺乏災情勘查車執行各項消防救災勤務，慷慨解囊捐贈約新臺幣100萬元災情勘查車1輛，內部配備LED警示燈、警報器、無線電等裝備，可執行各種災害搶救、災情查看回報、狹小巷道搶救及獨居老人弱勢團體關懷等，此義舉不但充實本市消防救災車輛，強化災害搶救之效能，拋磚引玉更是社會楷模、義行典範。今日落成啟用及捐車儀式，將大幅改善消防人員辦公環境及消防車輛出勤動線，提升救災救護效能，讓當地民眾的安全更有保障。發稿人：秘書室   股長 林婉茹    06-2975119分機2151",
    "tags": ""
}