{
    "published": "2015-12-02",
    "title": "駐台以色列經濟文化辦事處新任代表拜會市府 將建立未來雙方合作機制",
    "department": "",
    "url": "https:\/\/www.tainan.gov.tw\/News_Content.aspx?n=40853&s=166429",
    "content": "今(2)日賴清德市長、劉世忠副秘書長和新聞處吳堂成處長於市府接見新任駐台北以色列經濟文化辦事處代表游亞旭先生(Asher Yarden)，雙方針對未來合作交流進行意見交換。    賴市長指出，雖然臺灣和以色列在地理位置距離遙遠，但是臺以兩國在眾多條件非常相似，尤其共享重要的民主價值。市長特別讚賞以色列近年來在對抗乾旱的「滴灌」技術，亦或是再生能源的發展，都是世界的領頭羊。希望透過學習以色列成功經驗，為全世界環境盡心，讓地球永續發展。    游代表表示，非常同意賴市長的見解，認為兩國有太多相似的地方。他將臺以兩國比喻為被孤立的島嶼：臺灣是地理上定義的孤島，而以色列雖然緊連著許多國家，但在文化、宗教、經濟、軍事等都與相鄰國家差異甚遠。另外，游代表提到目前以色列汙水回收率是全世界第一，已達78%。相較於第二名的西班牙和澳洲的23%，相距甚遠。他則樂於結合臺灣高科技產業，及以色列的創新技術，建立雙方合作機制。    游代表更進一步表示，他發現臺以兩國人民皆擁抱兩個重要的價值觀，家庭和教育。兩國投注了許多心力在孩子的教育，對於自我的文化認同和人格的養成，影響甚鉅。    劉副秘書長則補充，正因為臺灣人對教育的重視，臺南市政府正積極推動英文為第二官方語言，也是全臺第一個將「英語作為第二官方語言」的城市，雖然是十年計畫，但市府非常努力推廣，希望臺南成為真正的國際城市。",
    "tags": ""
}