{
    "published": "2011-03-16",
    "title": "原按自用住宅用地稅率課徵地價稅之土地如不符規定時，別忘了向地方稅稽徵機關申報",
    "department": "",
    "url": "https:\/\/www.tainan.gov.tw\/News_Content.aspx?n=40854&s=50822",
    "content": "臺南市政府稅務局表示：所謂自用住宅用地，依土地稅法第9條規定，係指土地所有權人或其配偶、直系親屬於該地辦竣戶籍登記，且無出租或供營業用之住宅用地。現行地價稅一般用地係按10&permil;至55&permil;稅率累進課徵，自用住宅用地之稅率只有2&permil;，不參與累進，所以，當您的土地經申請核准改按自用住宅用地特別稅率課徵，至少可為您的荷包省下4倍的地價稅負擔。但當地上房屋有出租、供營業使用或戶籍遷出等適用特別稅率之原因、事實消滅時，而未主動於30日內向所屬稽徵機關申報改按一般用地稅率課徵地價稅，一經查獲，除追補稅款外並應處以罰鍰，提醒納稅義務人注意。發稿人：陳淑惠　　　　　　　　　電話：06-2119627",
    "tags": ""
}