{
    "published": "2011-03-16",
    "title": "室內裝修重新施作、更改或更換新建材或建築裝修材料老舊失去防火時效與功能情況，皆應辦理室內裝修。",
    "department": "",
    "url": "https:\/\/www.tainan.gov.tw\/News_Content.aspx?n=40854&s=154272",
    "content": "公供眾使用建築物及經內政部認定有必要之非供公眾使用建築物，應由起造人、所有權人、使用人辦理室內裝修。室內裝修係指除壁紙、壁布、窗簾、家具、活動隔屏、地氈等之黏貼及擺設外包括固著於建築物構造體之天花板裝修、內部牆面裝修、高度超過地板面以上一點二公尺固定之隔屏或兼作櫥櫃使用之隔屏裝修，以及分間牆變更。\n目前營業場所之室內裝修多併同變更使用執照辦理，惟營業場所於完成變更使用執照，常有室內裝修重新施作、更改或更換建材，或建築裝修材料老舊失去防火時效與功能情況，亦皆屬應應重新辦理室內裝修，市府亦將加強該類室內裝修稽核，以維護市民生命財產安全。室內裝修有違反規定者，將依建築法第九十五條之一規定處建築物所有權人、使用人新臺幣六萬元以上三十萬元以下罰鍰，並限期改善或補辦，逾期仍未改善或補辦者得連續處罰；必要時強制拆除其室內裝修違規部分。\n 發稿人：工務局使用管理科一股卜少光 電話：06-3901383",
    "tags": ""
}