{
    "published": "2012-01-19",
    "title": "臺南「安平」入圍臺灣十大觀光小城初選名單",
    "department": "",
    "url": "https:\/\/www.tainan.gov.tw\/News_Content.aspx?n=40854&s=139545",
    "content": "　　　　交通部觀光局於去(100)年十月辦理「臺灣十大觀光小城」遴選活動，各縣市政府提報具「十大觀光元素」特色之小城參與評選；市府觀光旅遊局特別遴選安平區以「在地文化」為主要觀光元素，並以「臺灣之名源自安平」為主題，從眾多報名參賽的各縣市觀光小城中脫穎而出，入圍第一階段初選，並將代表臺南市進入第二階段評選。　　　「臺灣十大觀光小城」需具「民俗宗教」、「在地文化」、「原民部落」、「溫泉」、「創新」、「當代文化」、「登山健行」、「追星」、「生態旅遊」及「自行車」等十大觀光元素之一，交通部觀光局分兩階段遴選，第一階段以書面審查，於今(18)日公布全台17個入圍小城；第二階段則由17個入圍小城選出前10大觀光小城，以「評審團評分機制」(書面資料、簡報答詢、現勘等，佔80%)及「民眾票選機制」（網路票選及明信片投票，佔20%），兩者成績加總，遴選出臺灣十大觀光小城，得獎小城將獲得交通部觀光局專案行銷推廣，並成為未來國際行銷的重要景點，藉此吸引國內外旅客走訪，帶動地方經濟發展。　　　台南市政府觀光旅遊局表示，安平舊稱「大員」，是台灣名稱的由來，故以「臺灣之名源自安平」作為這次小城的主題，擁有其他小城無法相比的歷史高度，還有全台許多第一：「臺灣第一城-熱蘭遮城（安平古堡）」、「臺灣第一鎮-熱蘭遮城市鎮」、「臺灣第一國際貿易港-大員港」、「臺灣第一洋行-德記洋行」、「臺灣唯一運河-安平運河」、「臺灣第一西式砲台-億載金城」，荷治、明鄭、清朝、日治等不同時期所遺留下來的歷史足跡，台灣三百多年來最精彩的歷史，皆化作優美的古蹟留存在安平，對於安平能入圍觀光小城初選，非常高興卻也不意外。　　　　安平區長林國明表示，安平因緣際會的由荷蘭人佔領躍上世界舞臺，開啟臺灣近代史的新頁，安平在不同時期的發展，留下不同發展的軌跡，擁有豐厚的歷史文化資產，是臺灣近代歷史的發源地，再加上近年來政府積極持續投注龐大資源改善旅遊軟硬體設施，如：安平環港觀光、低碳安平等重大計畫，不僅整合觀光資源，建立更完善的旅遊環境，在地傳統文化及古蹟也在公部門及民間部門共同努力下保存下來，成為安平主要旅遊特色，特別是安平素有「劍獅的故鄉」之稱，這幾年也在產官學界努力下，成功的將祂原本具有趨吉避凶意象，發展出具特色的眾多文創產品。此外，包括蝦捲、蜜餞、蚵嗲等傳統美食也是造訪安平不可錯過的一環，因此市府特地針對安平也推出「米其林旅遊路線」，將安平豐厚歷史古蹟、饒富趣味的美食小吃、文化底蘊與友善人情、陽光美景規劃為深度旅遊路線，提供給遊客。　　　　安平雖然具有豐富觀光資源而入圍「臺灣觀光十大小城」遴選初選，但本次活動第一階段以「在地文化」入選的尚有彰化鹿港、高雄美濃、新北市瑞芳、苗栗三義、桃園大溪、花蓮瑞穗、金門金城、馬祖北竿及澎湖馬公等9個小城，未來在第二階段將成為安平的競爭對象，第二階段選拔將包括評選委員成績及民眾網路投票結果，請臺南市的市民在第二階段一起為「安平」加油集氣，讓「臺灣第一城」的安平成為「臺灣十大觀光小城」，讓台南的城市文化踏上國際舞台！　　　　聯絡人：台南市政府觀光旅遊局 張淵柏 科長 聯絡電話：0937-347016聯絡人：安平區公所 蔡群儀 主任秘書 聯絡電話：06-2951915轉1002　　",
    "tags": ""
}