{
    "published": "2012-01-17",
    "title": "利用智慧手機APP查詢臺南公車，悠遊臺南SO EASY！",
    "department": "",
    "url": "https:\/\/www.tainan.gov.tw\/News_Content.aspx?n=40854&s=140543",
    "content": "因應101年春節假期來到，臺南市政府交通局即日推出「台南公車APP」智慧手機應用軟體功能服務，方便民眾下載並利用智慧手機查詢最完整、最即時的公車動態資訊，讓使用者在臺南地區搭乘或轉乘公車更加便捷，隨時利用「台南公車APP」悠遊大台南。為健全本市公車系統，提供臺南市公車E化服務，臺南市政府交通局自93年起已建置「臺南市公車動態資訊系統」，包括愛上巴士2384便民網站查詢（http:\/\/2384.tncg.gov.tw，含公車動態查詢及轉乘規劃查詢）、電話語音查詢（06-2998484我坐坐巴士巴士）、M-Tainan手機或PDA查詢（http:\/\/tourguide.tncg.gov.tw\/mobile\/TncgBus.html）、以及公車智慧型LED站牌等服務，可讓民眾隨時查詢公車動態即時資訊！而臺南市政府交通局為因應智慧型手機的發展趨勢與熱潮，更利用聰明公車多年來陸續建置的基礎與成果，針對智慧手機iPhone的ios與Android之作業系統開發「台南公車APP」，讓公車查詢的操作更加方便，並減少候車時間以有效規劃行程，使公車變得更聰明、更友善智慧手機的ios與Android作業系統目前已可提供使用者至App Store及Android Market下載使用（搜尋「台南公車」即可），操作手如詳附件。「台南公車APP」應用服務功能如下：1.【動態公車資訊查詢】：讓您快速掌握大臺南地區各線公車即時動態資訊。2.【附近站牌查詢】：提供站牌位置地圖顯示，並顯示各路線到站資訊，讓您聰明決定搭乘路線。3.【我的最愛】路線收納功能：方便使用者多次查看，節省您的查詢時間。4.【轉乘查詢服務】：關鍵字輸入，查詢結果以多方案資訊呈現，提供您最佳的E-Bus轉乘建議。\n發稿單位：臺南市政府交通局 陳淙祺 (06)3901329",
    "tags": ""
}