{
    "published": "2013-06-25",
    "title": "「臺南市東區竹篙厝段2110、2110-3、2111、2111-1、2111-27、2111-39地號等6筆公有土地設定地上權案」已於102年6月20日北上辦竣招商說明會，業者出席踴躍，意見充分溝通，說明會圓滿完成",
    "department": "",
    "url": "https:\/\/www.tainan.gov.tw\/News_Content.aspx?n=40854&s=128852",
    "content": "臺南市政府財政處辦理之「臺南市東區竹篙厝段2110、2110-3、2111、2111-1、2111-27、2111-39地號等6筆公有土地設定地上權案」已於102年5月31日正式公告徵求民間投資人參與投標，並於6月20日下午2時假臺北市信義區「國泰金融會議廳G廳」舉辦招商說明會，就本案之基地概況及招標文件重點，向潛在投資人進行簡報，達成雙向意見溝通與交流。 \n本案訂於102年7月16日上午9時截止收件，並於同日上午9時30分開標，歡迎各業界先進踴躍參與投標。\n\n\n附件下載\n招商說明會簡報資料\n(本簡報資料僅供投資人參考，實際資訊仍以民國102年5月31日正式公告招標文件為準)",
    "tags": ""
}