{
    "published": "2017-08-24",
    "title": "臺南市安平污水下水道系統大同分區啟動！",
    "department": "",
    "url": "https:\/\/www.tainan.gov.tw\/News_Content.aspx?n=40854&s=38494",
    "content": "為提供市民健康的居住環境及改善居家環境衛生，近年臺南市政府水利局積極辦理污水下水道建設，為使安平污水下道系統更趨完善，並提高用戶接管普及率，更推動大同分區污水下水道建設，並將大同分區污水下水道系統納入臺南市污水下水道系統第四期實施計畫，計畫期程民國106年~110年及第五期實施計畫，計畫期程年國111年~115年，預計在民國115年前完成大同分區污水下水道系統建設；其中第四期實施計畫已於106年2月獲內政部營建署核定，水利局亦於106年7月完成「臺南市安平污水下水道系統大同分區分支管網及用戶接管工程委託設計及監造技術服務」之發包作業，目前正著手規劃設計大同分區之污水管線工程。 大同分區範圍坐落於本市東區、南區及中西區，共涵蓋竹溪里、新生里、大林里、大忠里、大恩里、路東里、大德里、大福里、崇明里、東智里、五妃里、郡王里等12里，分區範圍南至生產路，北迄府前路，東達縱貫鐵路，西至南門路，目前正進行分區範圍污水管線之規畫設計，預計於108年發包主次幹管標，總長度約13公里，110年發包污水用戶接管標，預計總接管戶數約7,128戶，總工程經費約為7億8千萬，完成後預計可提升臺南市接管率約1.05%。 為讓民眾了解工程施工過程及其影響，未來在工程發包後將由施工團隊於開工後立即舉辦施工說明會，向民眾報告施工過程及注意事項，屆時請里民踴躍參加，並希望民眾能多加配合，共同提昇優質生活環境。 水利局呼籲，污水下水道建設不只改善居家環境衛生、營造永續的水資源，更為國際上國家競爭力重要評比項目，是社會現代化不可或缺的公共建設之一。完成污水下水道系統建設除改善當地居民生活品質外，更能藉由當地民眾配合市府推動污水下水道用戶接管建設，讓整個居住衛生環境更美好，享有優良的居住環境。",
    "tags": ""
}