{
    "published": "2017-08-15",
    "title": "第1至第3輪停電通知",
    "department": "",
    "url": "https:\/\/www.tainan.gov.tw\/News_Content.aspx?n=40853&s=166815",
    "content": "16點51分大潭電廠六部機同時跳脫，跳脫原因為中油供氣突然中斷，瞬間少了約四百二十萬瓩，系統頻率瞬間降低，導致低頻電驛自動卸載，造成全台多處發生停電情形。台中五號機因此事故鍋爐飼水水位過低跳脫，影響供電供電能力約五十二萬瓩。目前系統緊急處理中，因為考量晚上用電尖峰，目前實施緊急分區輪流停電18點起實施三輪，每輪三百萬瓩，每輪五十分鐘。   跳掉發電機要能重新並聯，大潭預計十九點陸續併聯。   緊急分區輪流停電：每輪三百萬瓩，持續五十分鐘 第一輪：影響237萬戶，遍及全省，ＡＢ兩組都有，影響饋線1427條饋線（1800-1850）  第二輪：195萬戶，1367條饋線  第三輪：236萬戶，1424條饋線  共668萬戶受影響台南地區部分： 台電新營區處通知18:00-18:50緊急輪流限電區域：官田工業區，北門部分區域白河區，隆田區後壁區下營區等部門區域 台電台南區處通知18:00-18:50緊急輪流限電區域：計停電128條線路，停電21萬4914戶。18：50-20:00第二輪緊急性分區輪流停電區域：新營，柳營，柳營科工區、北門部分地區、將軍、佳里、西港、七股、安定、新市、善化、山上、安南、中西、北、東、南、安平、仁德、歸仁、關廟、龍崎、左鎮、新化、玉井、楠西及南化區等部分。台電台南區處第三輪20：00-20：50停電通知: 計停電51條饋線，停電7萬2129戶!停電區域包含將軍、佳里、西港、七股、安定、新市、善化、山上、安南、中西、北、東、南、安平、仁德、歸仁、關廟、龍崎、左鎮、新化、玉井、楠西及南化區等部分。台電新營區處第三輪20:00-20:50緊急輪流限電區域：官田工業區，北門部分區域白河區，隆田區後壁區下營區等部門區域。",
    "tags": ""
}