{
    "published": "2012-09-19",
    "title": "七股樹林首創紙造水牛",
    "department": "",
    "url": "https:\/\/www.tainan.gov.tw\/News_Content.aspx?n=40854&s=131943",
    "content": "七股樹林里長黃寶田說，有時在樹仔腳下會唱起老歌：阿爸牽水牛，牽到田岸邊&hellip;；這首歌除唱起來讓人琅琅上口外，曲中水牛幫農戶辛苦耕作的憶境，是讓人懷念、感恩的兒時記憶。 為飲水思源，讓孩子了解水牛文化，樹林里也在社區活動中心外，以50年代鄉下牛車佈置為主題意象，並由王玉墻先生無私提供所珍藏的牛車，使牛車成為社區裝置藝術角，傳承社區文化。現今獨留車身，水牛已不復見，地方長輩深覺意象少了故事完整性，因此，在七股區長莊名豪的建議下，並獲得台南市環保局長張皇珍的支持，由公所輔導社區回收各機關學校廢公文紙、報紙，以廢紙作為主材料，經由環保局中西區隊郭雅玲及郭祈財老師指導，打造全國獨一無二的社區新亮點─「紙有樹林－水牛回家」為主題意象。  台南市環保局長張皇珍表示，樹林社區以落葉堆肥作為鹽地蕃茄、苦瓜、洋香瓜的培育基質，將沿海漂流木活化為藝術品，首創環保白鶴風車，白鶴相關文創品，都是未來推動為大台南市環保低碳社區的良好基礎。莊區長名豪表示，樹林里寶安宮的白鶴陣，象徵健康、長壽，未來將和村民以傳統藝陣的方式注入創意及活力，將樹林社區推廣成為全國複合式環保「白鶴社區」，大力研發白鶴文創商品、生產低毒害鹽地農業蔬果。特別是先前請台南市環保局協力以廢紙再利用打造社區「環保白鶴」入口意象，2隻紙作白鶴已完成，預計本年10月中揭牌亮相。莊區長認為將廢紙作為藝術文創，主要在提高社區民眾的環保意識，並鼓勵社區民眾參與水牛營造工作，預計蒐集300斤廢紙經粉碎後製作成全國第一隻紙造戶外水牛，象徵社區純樸、刻苦耐勞的精神。另七股樹仔腳社區有逸樂社、漂流木藝品，白鶴陣、白鶴環保風車、鹽地蕃茄、生態公園、寶安廟埕、尋找虎爺、太陽能堆肥製作等，深具地方特色，未來將協助社區形塑包裝成地方產業，帶動社區發展。莊區長名豪表示，七股除擁有黑面琵鷺生態保育、漁村風貌、鹽山及鹽博外，未來樹林白鶴社區將成為七股觀光新亮點，屆時歡迎全國好友到七股樹林參觀一遊。發稿人：民政課方又亭 聯絡電話：7872611*260",
    "tags": ""
}