{
    "published": "2012-09-13",
    "title": "台南文化中心9\/14、9\/15HuiDance匯舞集創團首作《門The Door》",
    "department": "",
    "url": "https:\/\/www.tainan.gov.tw\/News_Content.aspx?n=40854&s=52636",
    "content": "旅歐編舞家蔡慧貞回國創匯舞集，於故鄉發表創團首作《門The Door》多媒體藝術家張博智、義大利編舞家Francesco共同打造身與影共舞的跨國創藝舞作跨界舞蹈作品《門The Door》台南初試啼聲，備受各界期待「HuiDance匯舞集」為旅歐舞蹈家蔡慧貞於2011年創立，「匯」代表聚集、整合創意與創藝的概念，期望以專業舞蹈為根，匯集各領域人才的力量，發展多元風格的舞蹈劇場作品，並發掘、培養有潛力的南方舞者，為南方舞蹈藝術發「身」。 一直都同時發展表演與編舞的藝術總監蔡慧貞，曾二進二出雲門舞集，為追求表演創作變化與創新，2007年決定出國發展，遠赴瑞士於伯恩芭蕾舞團專職，但身在國外工作即使擔任首席舞者，蔡慧貞思鄉的情緒從未間斷，於是2011年決定回國創團作自己的作品，匯舞集即將於蔡慧貞的故鄉台南發表創團首作。「門」代表進出、連結各個獨立的空間，甚至能夠超越空間，蔡慧貞思念臺灣時就期待有座任意門帶她通往家鄉，連結親情、友情、愛情和鄉愁。編舞家蔡慧貞與 Francesco D&rsquo;Astici 在《門》這齣作品中，更期望能結合東西方肢體訓練與旅歐舞蹈經驗，尋找新的肢體運用與動作元素，讓身體成為思想的語言，創造出更多視覺的可能性，並與台灣的觀眾分享不同的舞蹈和生命體驗。本次創團首作，蔡慧貞除了邀請參與多齣百老匯音樂劇演出的義大利編舞家Francesco 擔任編舞；曾參與幾米音樂劇影像製作的新媒體藝術工作者張博智創作影像設計，台南人劇團團長李維睦擔任舞台設計、劇場服裝設計師林秉豪擔任服裝設計；也克服南部舞者短缺的問題，邀集南部優秀舞者，也是蔡慧貞之前在雲門舞集的同事：王維銘、潘潔尹，及南部優秀的青年舞者勞舞祖．達布拉卡斯、蘇尹聆、黃依涵。匯舞集帶領優秀的製作團隊，誠摯製作，共同打造影舞相伴的迷幻創藝旅程。即使創團之路艱辛，匯舞集首次演出仍得到台南在地企業贊助支持，如傑聖科技股份有限公司、財團法人可成教育基金會及華台科技大力協助，共同慷慨支持舞團創團製作。「HuiDance匯舞集」《門》全台首演即將於9\/14、9\/15於台南文化中心原生劇場開始，購票請洽匯舞集0985-283-085梁小姐。發稿人：藝文推廣課陳耀堂連絡電話：06-2692864#603",
    "tags": ""
}