{
    "published": "2016-02-04",
    "title": "後壁白河觀光T-Bike將於2月5日開始試營運 歡迎遊客前往體驗",
    "department": "",
    "url": "https:\/\/www.tainan.gov.tw\/News_Content.aspx?n=40854&s=139606",
    "content": "後壁白河觀光T-Bike將於2月5日開始試營運 歡迎遊客前往體驗擁有濃濃鄉村風情的後壁區及白河區，其綠色隧道與農田景緻令人心曠神怡，且因地勢平坦，非常適合騎乘自行車，市府觀光旅遊局規劃的「後壁白河米蘭蓮花線」自行車道亦於104年度榮獲全國十大自行車路線特別獎殊榮。為推廣遊客以低碳樂活的方式，體驗農村旅遊與欣賞自然美景，觀光旅遊局在後壁及白河區推出觀光自行車租賃系統(簡稱觀光T-Bike)，預定於105年2月5日(星期五)開始，為期2個月試營運，期間不收費用。觀光T-Bike共規劃5處租賃站，2月5日將開放第一階段3處租賃站，分別為後壁菁寮無米樂旅遊服務中心、小南海風景區的普陀禪寺及白河7-11新蓮鄉門市。試營運階段由2月5日至4月5日將完全免費，目前有提供30台自行車供租借，歡迎民眾踴躍試騎。各站皆以智慧型租借系統採無人管理方式，可甲地租乙地還，只要使用悠遊卡、一卡通或信用卡，加上手機認證，即可立即租借。民眾如果租借不到亦可到其他民間店家租借，例如位於後壁火車站的慢慢租車(僅假日營業，平日可電話預約)、位於林初埤的樂活單車生活館(僅於木棉花期大約3月份營業，其他期間請以電話接洽)、位於白河市區的捷安特(瑞發車行)及土溝美術館等，民間業者租賃價格亦屬親民合理，且可提供不同的車型，部份業者並可預約導覽服務。春節期間如吃膩了大魚大肉，想走出擁擠的人群，不妨來趟健康養生的樂活輕旅行，歡迎來白河後壁騎自行車體驗農村生活，以擁抱田野拜訪春天的方式，迎接嶄新的一年。觀光T-Bike客服專線：0988-865-215(一)第一階段各站點車格數(總共30台自行車周轉)                                    站點                                    車格                                                    後壁菁寮無米樂旅遊服務中心                                    16                                                    後壁小南海風景區普陀禪寺旁                                    10                                                    白河7-11新蓮鄉門市                                    19                                                    總計                                    45                        \n(二)周邊民間租賃業者                                    周邊租賃店家                                    地點                                    備註                                    聯絡電話                                                    慢慢租車店                                    後壁火車站                                    平日需預約                                    0935-033043                                                    樂活單車生活館                                    林初埤                                    僅木棉花期營業                                    0938-619027                                                    土溝農村美術館                                    土溝農村                                                                        06-6874505                                                    白河捷安特自行車店(瑞發車行)                                    白河市區                                                                        06-6854527",
    "tags": ""
}