{
    "published": "2014-07-29",
    "title": "2014中西區「做16歲」活動，府城青少年感恩、尊親、「轉大人」",
    "department": "",
    "url": "https:\/\/www.tainan.gov.tw\/News_Content.aspx?n=40854&s=138045",
    "content": "農曆七月感恩月，也是七夕情人節，臺南「做16歲」轉大人活動於8月2日上午陸續在臺南各廟宇登場，中西區廟宇有開隆宮、臨水夫人媽廟、永華宮等廟宇舉辦「做16歲」活動，五條港發展協會亦與在地學校學子結合辦理「做16歲」系列活動，讓青春少年學習尊親、感恩「轉大人」，期許青少年未來能肩負起城市下一世代的繁榮發展。在七夕日之時，開隆宮、臨水夫人媽廟是許多家長帶領屆滿16歲的兒女前往「做16歲」著名廟宇，廟方依循成年禮儀式舉行上香祈福、鑽轎亭儀式。永華宮「做16歲」活動除為里內青少年辦理「做16歲」活動，也提供「做16歲成年禮」紀念紅綵帶給參與「做16歲」的青少年作紀念，並透過「奉茶」給父母親及長輩的儀式，表示子女的孝順心及感恩情，父母親以疼惜的叮嚀與期許，送給兒女一個成長的紅包，與兒女共享「做16歲轉大人」的喜悅。五條港發展協會「做16歲」成年禮活動，除與寺廟崇福宮、神興宮、集福宮結合鑽轎亭儀式及西式教堂活動外，更安排苦力挑擔、扛米體驗的成長活動，為青少年在「轉大人」的過程中，感受父母的辛勞與成長的責任。感恩、尊親「轉大人」，讓「做16歲」寺廟擠滿人潮，在傳統宗教儀式外，更表彰尊親感恩之孝心及精神，也洋溢著及文化習性的熱鬧感及尊親的感恩心。「做16歲」是府城多年來特有的民風習俗，在臺灣民間信仰中，對孩兒的主要保佑神明有七娘媽、註生娘娘、鳥母﹝婆姐﹞，三種神明職責不同，小孩子從受孕成胎一直到16歲長大成人，不同階段都有不同的守護神來保佑孩子平安成長。 臺灣民間的成年禮稱作「作16歲」，家中有年滿需歲16歲的少年、少女，在農曆7月7日當天要準備各項牲禮、麻油雞、油飯、麵線、四果、紅龜粿等供品，感謝神明的保佑，連同牲禮祭祀完後，由父母或長輩高舉起七星亭背對廟門，讓孩子自後往前由七星亭下鑽過，然後再自七娘媽的供桌下，匐匍鑽行三圈，男孩起身後須往左繞三圈，稱「出鳥宮」，表示完成成人禮已長大成人了，「做16歲」的意義，在於讓孩子瞭解自己已成年，從此要對自己的言行負責。",
    "tags": ""
}