{
    "published": "2014-07-21",
    "title": "鄰里公園破400座  永康兒一兒二公園啟用",
    "department": "",
    "url": "https:\/\/www.tainan.gov.tw\/News_Content.aspx?n=40853&s=174971",
    "content": "（永華市政中心發布）打造「一區一公園」，永康區兒一及兒二公園今（21）日正式啟用，為當地再添兩處綠地。市長賴清德致詞時表示，歷經前任縣、市長以及工務局這三年來的努力，台南市鄰里公園已超過400座，今日啟用的兒一、兒二公園佔地雖僅有0.97公頃，但小而美的公園仍可發揮功效，作為社區居民休閒之用，提升當地市民生活品質，歡迎居民多加利用。永康區兒一、兒二公園位於現有砲校區旁計畫特定區（砲校遷移後將開發為永康創意設計園區），兒一公園位處東橋十二街；兒二公園位於東橋七街與東橋十街交叉口。兒一公園面積約0.24公頃，以都市中的鄰里小公園為構想，闢設舒適安全的內外步道，並串連街角與內部遊戲區，藉由藝術陶板及解說牌，讓孩童可以在自然環境中學習；兒二公園面積約0.73公頃，利用好望角導入大橋小橋歷史解說，並以步道的概念，使用藝術陶板來呈現，園內除新闢環狀步道外、植物解說牌及再生材料的使用，更讓孩童從小養成愛護環境的觀念。賴市長指出，縣市合併後，永康區為最大行政區，市府對於永康的建設不遺餘力，近三年投入85億經費，道路開闢16案、路平與維護25件、公園路燈及開闢35件，其中還不含治水預算。未來永康砲校遷移後，可望進一步帶動當地發展。工務局長吳宗榮指出，園區內種植阿勃勒、紅花風鈴木、台灣欒樹等喬木共175棵，灌木有桂花、馬櫻丹、朱槿、月橘等共計3600株。另外，為了增加新開闢的兒一、兒二公園內綠蔭效果，未來將移植砲校內現有的大樹，配合園區內整體規劃進行移植作業。工務局表示，經過開闢後的永康區兒一及兒二公園，將可提供舒適安全的環園步道，透過不同材質與解說的導入，創造平面空間的質感與植栽層次變化，同時串連各遊憩空間與休憩解說廣場，屆時將可先行提供當地區民一處休閒環境，並替未來的永康創意設計園區打造低碳樂活的休閒空間。颱風麥德姆接近台灣，賴市長藉今日記者會呼籲全體市民做好防颱準備，多一份準備、少一份損失，並要求各相關單位及區里啟動防颱機制。賴市長指出，市府自籌16億應急治水工程已於汛期前完工，並疏通3000公里側溝、開蓋清理1000多條雨水下水道，總長98公里；河川疏濬450公里。另外，35座抽水站已經完成，252台移動式抽水機也已就定位，呼籲所有市民朋友一起做好防颱準備，將颱風可能帶來的損害降到最低。",
    "tags": ""
}