{
    "published": "2015-10-22",
    "title": "對抗登革熱，台南觀光旅遊局強推三波段振興觀光方案",
    "department": "",
    "url": "https:\/\/www.tainan.gov.tw\/News_Content.aspx?n=40854&s=139268",
    "content": "對抗登革熱，台南觀光旅遊局強推三波段振興觀光方案 為了提振因登革熱而受到影響的旅遊產業，觀光旅遊局全力規劃，推出一系列振興觀光方案，透過具體作為帶動觀光，準備好敞開大門再度迎接民眾重回台南。 從即日起至年底有多場活動接力上陣，包括清燙牛肉節、台南美食節地區產業文化節系列活動以及原色聖誕燈節等，以多元豐富的旅遊內容喚起民眾對旅行台南的美好記憶。台南市政府昨（21）日於永華市政中心召開市政會議，會中觀光旅遊局局長王時思陳報「三波段振興臺南觀光方案」，規劃自10月到12月間，將分別以「優惠促銷期」、「品牌口碑擴散期」及「活力高峰期」為階段性主軸推出多元振興方案，經由不同面向、不同階段的努力，讓台南觀光儘速復甦。今年登革熱疫情影響臺南的觀光旅遊，台南市政府努力的不僅是讓台南整體觀光到年底時不只是復甦，也能延續到明年春節，展現另外一波台南旅遊的高峯。觀光旅遊局局長王時思表示，最近數週登革熱確診病例已持續呈下降趨勢，經過這陣子的休養生息，台南已經準備好重新迎接遊客的到訪，而台南民間觀光業者的活力一直是台南觀光的最大動力，本次振興觀光方案除了推動多項產業觀光活動，更與在地業者結合推出各項產業促進方案，以台南人的團體力量喚回全球觀光客。即日起直到年底，觀旅局緊鑼密鼓推出一系列觀光活動，尤其將以美食領軍打頭陣，吸引觀光客回流，11月份台南清燙牛肉節登場，以台南旗艦美食喚醒台南美食魂。11月14~29日將舉辦包含清燙牛肉、牛肉爐、牛腩湯、炒牛肉等四大牛肉料理的「美味人氣大賞」，各飯店餐廳也精心推出「創意牛肉料理」行銷本市出名的溫體牛肉。另外「美食旅行團」則藉由達人領團及揪團，帶領遊客吃遍臺南市牛肉美食，還有臉書留言抽免費雙人旅遊等超值優惠，機會難得千萬不能錯過！「2015台南美食節」（12月2~19日）則接續清燙牛肉節之後登場，將以台南美食的五感體驗述說屬於台南美食的故事。今年度臺南美食節將從在地職人出發，搭配美食名家與藝術表演，讓民眾可以用不同的角度去認識臺南的特色美食內涵，讓美食不僅僅是吃的享受，也是一種在地文化的重要體驗。此次活動透過五大主題&mdash;「總鋪師手路菜」、「府城老味道」、「少年巷仔內」、「農鄉人情味」、「府城小吃宴」，訴說台南美食文化，讓民眾傾聽這些經典料理背後的甘苦故事，希望藉此誠摯邀請民眾來暢遊台南，更多內容請至「2015台南美食節」活動網站（http:\/\/tnyummy.tw\/）查詢。 年底充滿歡樂氣氛的聖誕佳節也即將到來，觀光旅遊局延續往年傳統在國立台灣文學館（12月6日）及新營文化中心（12月11日）舉辦聖誕點燈儀式。今年以聖誕樹策展的概念執行，以白、紅、綠三原色為設計元素，規劃四個燈區展出，更在同一設計主軸上結合民間業者自行佈置的聖誕樹，擴大活動規模，讓全台南在歲末年初時處處洋溢著希望與祝福。 觀光旅遊局除了舉辦多場精彩活動之外，各家業者也聯合推出多項優惠好康，集合政府和民間資源的多元振興方案，就是希望再創台南觀光旅遊的好口碑，鼓勵遊客重新找回獨衷台南的情感，欲瞭解更多活動詳情及優惠內容，請上「台南觀光」網站（http:\/\/tour.tainan.gov.tw\/）查詢。新聞聯絡人：觀光旅遊局觀光行銷科張科長淵柏 0937347016觀光旅遊局觀光行銷科郭股長俊麟 0955310995",
    "tags": ""
}