{
    "published": "2016-09-08",
    "title": "9月10日晚上六點半在中西區清水寺前再現「梁山伯與祝英台」黃梅調電影",
    "department": "",
    "url": "https:\/\/www.tainan.gov.tw\/News_Content.aspx?n=40854&s=135412",
    "content": "中西區公所將在這週六(9\/10)晚上六點半，於清水寺前(開山路3巷10號)放映膠捲老電影，1963年發行的《梁山伯與祝英台》將透過35mm碳精棒骨董放映機，照亮清水寺歷史街區，重現在市民朋友眼前。本活動原訂9\/3舉行，因該日氣象預報降雨機率極高，考量觀賞品質及保護珍貴電影膠捲，故順延至這週六(9\/10)晚上六點半。本次活動是由臺南藝術大學音像紀錄與影像維護研究所助理教授曾吉賢指導規劃，並提供珍藏的梁祝電影膠捲，找來放映師張環裕師傅以碳精棒放映機在清水寺重現「廟口電影」放映情景，引領觀眾穿越時空回到1963年，見證這部改寫臺灣電影史、震撼全臺的黃梅調電影。播映當日將展示「宮古座（後延平戲院、今為政大書城）」老照片，以及梁祝一片1963年在臺南放映時的新聞剪報，更精心製作了梁祝人型看板，歡迎市民朋友們前來留下美麗的倩影，一起沉醉在黃梅調唱曲的淒美愛情故事之中。《梁山伯與祝英台》1963年在臺首次上映，即累積近千萬的票房收入，在台南的宮古座（後為延平戲院）放映時，連續賣座兩個月之久！該片扭轉了當時以放映西片為主的電影市場，開啟重視國片的風氣，更是臺灣國語電影起飛的重要分水嶺。該電影全部歌曲皆採用黃梅調演唱，每曲皆紅極一時、膾炙人口，時至今日，仍是許多老一輩長者琅琅上口的經典。本活動僅此一場，如天候不佳，放映場地將改至「永福、小西、三民里聯合活動中心」（地址：中西區府前路一段260號）播放，原活動現場（清水寺前）將由專人協助指引告知。~電影「梁山伯與祝英台」小檔案~出品年份：1963年出品公司：香港邵氏電影公司影片長度：122分鐘導演：李翰祥演員：凌波、樂蒂主演中西區公所(電話：06-2267151分機322)",
    "tags": ""
}