{
    "published": "2012-10-04",
    "title": "101年度原住民學生升學優待取得文化及語言能力證明考試訂於101年12月15日（星期六）舉行，請踴躍報考。",
    "department": "",
    "url": "https:\/\/www.tainan.gov.tw\/News_Content.aspx?n=40854&s=130159",
    "content": "行政院原住民族委員會辦理101年度「原住民學生升學優待取得文化及語言能力證明考試」，將於本年12月15日（星期六）舉行考試。    報名時間：101年9月25日起至10月26日受理報名，報考人得選擇以學校團體或個人方式報考，一律採取「網路報名」並「通訊郵寄報名表」兩個階段報名方式。    報考對象：以101學年度（即101年8月起）就讀國中二、三年級；高級中學或職業學校二、三年級；五專四、五年級與二專二年級學生或具同等學力之原住民學生為報考對象。    考生服務專線：02-2321-0191    相關考試資訊及報名簡章可至http:\/\/ipt.sce.ntnu.edu.tw\/101student\/news.php 查詢下載    另可至本府6樓民族事務委員會（安平區永華路2段6號）索取紙本簡章，份數有限，領完為止，2990290蔣小姐。",
    "tags": ""
}