{
    "published": "2012-10-07",
    "title": "法籍學生楊飛幻獨立發起台南足球聯賽 賴市長期勉發展城市交流",
    "department": "",
    "url": "https:\/\/www.tainan.gov.tw\/News_Content.aspx?n=40853&s=175155",
    "content": "（永華市政中心發布）  城市交流又一章！由台南大學體育系研究生楊飛幻獨立發起的台南足球聯賽，今（7）日起至明年7月止，在台南崑山科大舉行，市長賴清德受邀前往主持開幕式，期勉發展成為城市交流，培養深厚的友誼。  台南足球聯賽發起人楊飛幻，本身是法國梅斯城市足球隊員，目前是台南大學體育系研究所的學生，秉持號召足球迷齊聚一堂，推展足球運動的決心，今年再度發起足球聯賽，並幸有中華職業足球聯盟協會理事長吳山駿夫協助，合作辦理為期9個月的賽事。賴市長受邀前往主持開幕式，肯定楊飛幻的用心，尤其是對於楊飛幻推展足球運動的精神，足以證明其已融入台南生活。  賴市長表示，看到足球聯賽成員，來自全國各地足球迷共同參與，25%為外國人、75%本國人，他期勉藉此發揮三大功能，一、不只市民之間情感交流，也能成為國際情感交流場合，二、藉由足球聯賽的賽事，培養足球人口，技術提供，三、發展成為城市交流。賴市長強調，不一定要在足球技術上爭高下，而是要培養有誼的深厚。  楊飛幻特別拿出球員證贈與賴市長，表示感謝之意。楊飛幻指出，這項聯賽在去年首次推出時就有6支隊伍參與，今年又多了2支隊伍，規模更勝中華民國足球協會城市聯賽的7支隊伍，目前台南足球聯賽成員已有200名，若再加上成員家屬、朋友，則是一個逾1000人的足球家族！發稿人:新聞及國際關係處 宋金燕  電話:2991111-8154",
    "tags": ""
}