{
    "published": "2015-04-21",
    "title": "人力中心邀請城邦媒體集團首席執行長何飛鵬談公務員的當責管理！",
    "department": "",
    "url": "https:\/\/www.tainan.gov.tw\/News_Content.aspx?n=40854&s=158723",
    "content": "為型塑台南市府團隊「當責」組織文化，落實開放政府本質，提升城市競爭力，市府公務人力發展中心於今日(4\/21)舉辦名人講座：公務員的當責管理─人在公門好修行，邀請以其於職場文化、工作發展有精闢解析的城邦媒體集團-何飛鵬首席執行長蒞臨演講，分享當今公務人員職場經營之道，期許臺南市成為當責的城市。當日臺南市長賴清德、市府秘書長陳美伶及市府約180位主管皆到場參加。 臺南市長賴清德表示：何首席執行長出身公共行政卻轉行媒體取得成功，並進一步推動當責政治文化，對社會有深遠影響，讓他深感敬佩。賴市長也表示在全球化的洪流中，提昇政府競爭力刻不容緩，亟須當責文化的推行落實，也期許今日的主題當責文化在將來可轉化為臺南市政府的行政文化。 何首席執行長運用個人及職場工作經驗期勉市府公務人員，當公務人員應該抱持為民服務的心態，勿有非分之想，要能抵擋外界誘惑。公部門只有日出條款，沒有落日條款，近來也面臨官僚體系腐化、價值沉淪、劣幣效應、醬缸文化等問題。何首席執行長建議要打造當責的組織文化以扭轉前述局面，當責比負責更高一層次，就是人人多做一點，把沒人做的工作填滿。負責的組織還有三不管地帶，當責組織則是緊密交織，面臨問題應走當責迴路而非卸責迴路。當責者就是為不該負責的事負完全責任並力求一個好結果，負責者則只重過程但是不管結果為何。何首席執行長勉勵與會者，當責就是發揮「巧婦能為無米之炊」的精神，不要以沒人沒錢為藉口，就算缺乏外部資源，也要盡力用創意創新來達成目標。若機關單位能落實並貫徹當責文化制度，則可成為一個高效、成果、回饋、幸福的組織。 臺南市政府秘書長陳美伶表示：台南市四年來的努力組織文化有別於其他縣市政府。藉由今天何首席執行長的演講帶給市府同仁一些腦力激盪，改變機關既定的官僚文化，也驗證市府四年來的進步夠不夠。",
    "tags": ""
}