{
    "published": "2015-05-28",
    "title": "北區區公所辦理104年上半年度里長業務聯繫會報會議",
    "department": "",
    "url": "https:\/\/www.tainan.gov.tw\/News_Content.aspx?n=40854&s=136340",
    "content": "　臺南市北區區公所依年度計畫舉辦104年上半年度里長業務聯繫會報，擬藉由里長業務聯繫宣導市府重要施政理念及加強與基層聯繫，以增進市府團隊與里長及各機關單位彼此互動情誼。 里長業務會報活動訂於104年6月2日(星期二)下午4時30分假華興振興里聯合活動中心二樓大禮堂（林森路三段181號二樓）舉行業務會報。 本次會議除函請轄內全體里長、里幹事出席外，並廣邀市府民政、工務、水利、交通、環保、社會、衛生、教育、警察、都市發展、農業、戶政、臺電台南區營業處等相關單位列席。會中並安排公所各課室作年度施政工作報告，期能使各里長在推動市政上有更大助益。撰稿人：北區區公所 民政課(楊雅玲) 聯絡電話：06-2110711",
    "tags": ""
}