{
    "published": "2015-05-12",
    "title": "2015TNAF城市舞台─奇點劇團【大海之東】，歡迎民眾踴躍蒞臨觀賞。",
    "department": "",
    "url": "https:\/\/www.tainan.gov.tw\/News_Content.aspx?n=40854&s=138350",
    "content": "台南的詩篇、善化的記憶。當百年詩歌與當代劇場相遇，會激起怎樣燦爛的火花？「大海之東」是何方？那是異鄉還是家？奇點劇團【大海之東】訂於5月15日至17日(五至日)假善化慶安宮戶外廣場3場年度公演，歡迎民眾踴躍蒞臨觀賞。奇點劇團，創作的「起點」在台南！我們由專業表演藝術工作者組成，年輕活力、豐富的創造力與熱情，是我們的特質，我們喜歡台南，喜歡台南的生活步調、藝文氣息，我們知道劇場是有魔力能將一群人的心繫在一起！創團理念是開創多元藝術結合，進行大膽觀念性實驗性質、現場即興可能之劇場創作，要挑戰戲劇與觀眾的距離分界。【大海之東】帶你看見不同世代對家鄉、故土在價值觀上的分歧與異同，情感間的衝突與認可；藉由台灣本土詩歌的詠唱與意境具像的呈現，感受流寓、懷鄉與痕跡的三個主題的情懷和氛圍。從目加溜灣社到台南善化，時光在這塊土地上留下了什麼樣的蹤跡？追尋著「海東文獻初祖」沈光文先生的腳步，體會寄宿在詩篇裡跨越時空的思鄉之情，那是你與我也有著共同的情感記憶。【成立宗旨】1.堅持原創性的表演藝術創作，實驗創造新穎劇場感官體驗。2.關懷人文與地方文化。3.推廣「Stand-up Comedy」的表演形式，培訓表演藝術從業人才。【劇團經歷】2014 1月 《青鳥與北極星》 安平49人文咖啡館2014 2-3月 《奇點SHOW》春の季2014 3月 「身體x時間」表演訓練工作坊2014 4月 《A Day》 臺南文化中心國際廳原生劇場2014 5-6月 《奇點SHOW》Friday Night2014 6月 《奇點SHOW》 高雄 院子劇場2014 9月 臺北藝穗節《奇點SHOW》2014 9月 《奇點SHOW》嘉義市政府文化局演講廳2014 10月 《奇點SHOW》國立善化高中2014 10-11月《奇點SHOW》城市快樂頌2014 10-11月 「表演基礎與喜劇入門」工作坊2014 11月 《奇點SHOW》國立陽明大學邀演2014 11月 《奇點SHOW》長榮大學邀演2014 11月 2014彰化劇場藝術節《奇點SHOW》編導│郭峰任演員│李奎鋒、石松林、夏嘉隆、鄭得愛、王德安、紀媮鏵執行製作│鍾惠喻主辦單位：臺南市政府承辦單位：臺南市政府文化局協辦單位：財團法人台南市文化基金會、國立成功大學文創育成與研發中心、 國立臺南藝術大學、臺南市善化區公所、善化慶安宮演出地點：善化慶安宮-戶外廣場(台南市善化區中山路470號)演出日期：5\/15(五)19:00；5\/16(六)19:00；5\/17(日)19:00票 價：免費，座位有限，請提早進場。 (18:30開放入場)發稿日期：104年5月5日發 稿 人：奇點劇團 鍾惠喻聯絡電話：0911-413665",
    "tags": ""
}