{
    "published": "2014-12-12",
    "title": "名人講座邀請網路教父詹宏志董事長演講「一個城市的數位力與文創力─與台南朋友的交談」",
    "department": "",
    "url": "https:\/\/www.tainan.gov.tw\/News_Content.aspx?n=40853&s=168072",
    "content": "（永華市政中心發布）台南市政府為豐富府內中高階主管多元視野，發揮台南市豐沛的文化底蘊能量，尋求台南數位發展契機，以提升城市競爭力，市府公務人力發展中心於今(12)日舉辦名人講座：一個城市的數位力與文創力─與台南朋友的交談，當日特地邀請以其創意、對文化及網路趨勢與社會經濟問題的精闢解析，而獲得網路教父尊稱的PChome Online網路家庭國際資訊股份有限公司-詹宏志董事長蒞臨演講。市長賴清德除蒞臨現場表示感謝及歡迎外，並向詹董事長請益。 賴市長首先表示，很榮幸今天有機會邀請到PChome Online的詹董事長來台南為市府各高階主管做最精采的演說。賴市長說，詹董事長是社會學家、傑出作家、創業家，同時也是一位趨勢專家。詹董從事媒體工作30年，對社會的觀察非常銳利；創作了電影如悲情城市、牯嶺街少年殺人事件、戲夢人生等作品。同時他也是PChome Online數位產業中首屈一指。就因為他幾十年的歷練及本身的財富，成就他對文化、創意、社會經濟、網路趨勢等的評論可說是一字千金、擲地有聲。賴市長相信市府各高階主管在聆聽詹董事長的演講後，可以學到很多，包括第一、學到他的專業。好比文創力、數位網路力本身的專業，讓這個城市未來在發展文化創意產業，成為智慧城市，及對古都結合新文明成為數位科技城市，帶來幫助。第二、學到他敗而不餒的精神。詹董事長從不諱言他在網路的第一個報紙-明日報的失敗，也因為那次失敗，匯集了他下一次更大的力量。第三、學到他的方法、創意。賴市長認為市政府雖是公務部門，但不應該墨守成規，或光做例行性的工作，應該要學習創意，就有限資源解決工作上的困境，將效益發揮到最大。詹宏志董事長以行動錢包電子支付機制為開場白，以其多年的網路電子商務及金流服務經驗，分享如何打造一個簡政、便民、創新的優質行動生活服務，並可引用先進的數位友善思維，將南台灣打造成一個數位創業基地，建置全台最優質的多元語言觀光網站以及文創型數位企業聚落等數位力策略，來提升台南的數位力。詹董事長並提及：台南市已經是台灣最具文創力的城市，除擁有得天獨厚的歷史文化氛圍，還有值得驕傲的美食傳統，近年更致力於將文創與觀光進行結合，在這樣豐厚的文化基底下，一定可以將台南打造成一個具有生活、美食、節慶、故事、體貼的文化城市。最後賴市長贈送「天壇的一字匾」予詹董事長，希望未來不管在文創或是數位網路上都是第一人，詹董事長也回贈賴市長兩本他所著作有關台南觀光產業的書。",
    "tags": ""
}