{
    "published": "2014-04-29",
    "title": "2014鄭成功開臺353周年-湖樣巴圖~大湖文化特展  4\/29起精彩展出",
    "department": "",
    "url": "https:\/\/www.tainan.gov.tw\/News_Content.aspx?n=40853&s=174811",
    "content": "（永華市政中心發布）2014鄭成功開臺353週年系列活動-「湖漾巴圖－大湖文化特展」29日於鄭成功文物館開幕，由市長賴清德、內政部長陳威仁、金門縣長李沃士、日本平戶市副市長寺田勝嘉等多位貴賓共同剪綵及巡禮。賴市長表示，這是目前臺灣唯一完整展出代表器物「巴圖形石器」的展覽，他誠摯邀請全國民眾來臺南觀賞，更進一步了解臺灣的歷史。賴市長表示，今年是鄭成功開臺353週年，市府除舉辦中樞祭典以外，特別舉辦大湖文化特展，展出距今約三千多年前，先民食衣住行的各種情況。他說，有「還原燒」燒成的黑陶、「氧化燒」燒成的紅陶，以及彩陶，還有兵器、巴圖、稻米薏仁種植方式、紡紗等，內容豐富精彩，歡迎民眾把握良機來臺南探尋臺灣歷史。湖樣巴圖~大湖文化特展以3百餘件史前出土文物的考古文物呈現、互動遊戲及實景復原方式表現當時大湖文化的聚落空間配置，展出內容淺顯易懂並具教育推廣意義，相當適合親子一同前往觀賞，特展將從4月29日至10月31日於鄭成功文物館1樓展出。今年「湖漾巴圖－大湖文化特展」將史前時代往前推至距今約3,300年前的大湖文化時代，帶領市民朋友及國人一窺臺灣史失落的環節。「大湖文化」是在高雄市湖內區大湖遺址是最早被發掘的，1920年八田與一興建嘉南大圳時發現烏山頭遺址，開啟大湖文化研究序章。「大湖文化」蘊含著臺灣西南部平原先民的履跡，也是臺南發展史中不可或缺的拼圖，「湖漾巴圖－大湖文化特展」透過考古的發掘與研究，拼湊出大湖文化人的生活樣貌，串起依舊深埋藏在這塊土地上的片段臺灣史。為深化學術研究面向，臺南市政府文化局特別為今年的特展規劃「大湖文化特展專題講座」，邀請臧振華、陳玉美、李坤修、劉克竑、顏廷伃、林秀嫚、郭素秋、林淑芬等專家學者深入探討大湖文化，講座活動於5月1、2日（四、五）假文資保存中心國際會議廳舉行。另外，與樹谷文化基金會合作在展場規劃的教育推廣活動，分別於5\/3（六）、6\/7（六）、7\/5（六）、7\/18（六）、8\/2（六）、8\/15（五）、9\/6（六）、10\/4（六）等8個週六的上午10:30～11:30以及下午1:30～2:30各推出兩場「時光隧道DIY－大湖先民體驗區」，以深入淺出的說故事方式，吸引大小朋友進入大湖文化世界，DIY體驗活動，則邀大家學習先民器物藝術之美，歡迎市民朋友踴躍參與。",
    "tags": ""
}