{
    "published": "2018-07-19",
    "title": "107年度華美光學安衛家族教育訓練",
    "department": "",
    "url": "https:\/\/www.tainan.gov.tw\/News_Content.aspx?n=40854&s=207438",
    "content": "　　以歷年職業災害統計分析，常見墜落、感電、捲夾、被撞、倒塌崩塌等危害類型，就以墜落災害類型佔多數。勞工局於107年7月19日假華美光學科技股份有限公司辦理華美光學安衛家族教育訓練，透過集合訓練使家族成員了解墜落及感電危害，並採取危害預防等必要設備及措施，進而提升勞工防災意識。\n　　今日課程特別邀請南區職業安全衛生中心薛明勝技正前來授課，針對感電作業危害，從實際發生之職業災害案例中探討應如何改善，避免類似職災發生；另外墜落案例分析中指出災害類型、媒介物以及致災原因，進而採取必要之防墜措施，落實防護具之使用，以保障勞工作業安全。　　勞工局王鑫基局長對於華美光學科技股份有限公司在安衛家族工作推動上所做的努力表示肯定與感謝，並指出課程提到墜落及感電災害類型，應是家族成員們課後回到公司後所執行的重點，找出危害因子並且消除，才能有效降低職災發生的機率。　　本次華美光學安衛家族教育訓練，透過講師工安檢查的實務經驗分享，家族成員表示均有收穫，期盼能帶回事業單位提升安全衛生工作文化，守護勞工作業安全與健康。",
    "tags": ""
}