{
    "published": "2018-03-19",
    "title": "安平漁港「2018第一屆米米之星全國歌唱比賽」~帶您夢想起航",
    "department": "",
    "url": "https:\/\/www.tainan.gov.tw\/News_Content.aspx?n=40854&s=55035",
    "content": "「安平漁港」具備渾然天成的港灣及美景，近年來逐步朝觀光休閒方向發展。港區有許多特色商店進駐，其中「請上桌國際港灣」為提倡正當的休閒活動，特聘知名「周傑米歌唱培訓音樂學苑」辦理「2018第一屆米米之星全國歌唱比賽」，歡迎您用美妙的歌聲，傳遍安平漁港。\n 「2018第一屆米米之星全國歌唱比賽」開始接受報名，訂於107年5月19日(六)進行初賽、107年6月9日(六)進行決賽。獎金優渥，還有最佳造型獎、最佳人氣獎及最佳台風獎，歡迎16歲以上的朋友踴躍參加。\n 倘若您想圓夢或了解參賽事宜，歡迎加入line「ID:twentyfive3323612」，或撥打0930-100-078逕洽音樂總監周傑米老師，將竭誠為您服務。\n發稿人：臺南市漁港及近海管理所林淑蕙 電話：06-2991111-8273",
    "tags": ""
}