{
    "published": "2014-06-13",
    "title": "臺南市政府補助動保協會辦理流浪犬貓絕育",
    "department": "",
    "url": "https:\/\/www.tainan.gov.tw\/News_Content.aspx?n=40854&s=161681",
    "content": "台南市動物防疫保護處新聞稿發稿日期：103年6月13日標題：臺南市政府補助動保協會辦理流浪犬貓絕育臺南市政府編列600萬元預算獎補助本市合法立案之動物保護團體辦理流浪犬絕育450萬元，預定絕育流浪犬2,525隻，流浪貓絕育150萬，流浪貓949隻，目前已核定270萬元補助4個動保協會辦理2仟餘隻流浪犬絕育，113.9萬元補助6個動保協會辦理893隻流浪貓絕育，剩餘之補助款將再視執行狀況再提供各協會申請。103年流浪犬絕育補助辦理方式，將由本市動物保護管制隊進行負責捕捉、送到動物之家掃描晶片去除家犬及不適合原地暫置之犬隻後，再點交給受補助團體運至動物醫院絕育後運送暫置於捕捉地點照顧。而愛貓人士所關心的流浪貓絕育補助計畫，仍維持由動保協會進行捕捉絕育及暫置原地點。如民眾或動保團體想為流浪犬絕育，可聯絡本市動物保護管制隊(06-2965945)，將有專人協助辦理流浪犬絕育手術。如要通報流浪貓絕育可以向以下6個協會通報(臺南市保護動物協會趙祕書0910340480，臺南市尊重動物生命協會李總幹事0929137582、台南市流浪動物愛護協會郭理事長0912973937、臺南市人道救援動物協會劉理事長0980342091、台南市向葵關懷流浪動物協會杜小姐0928301662。由於流浪犬貓絕育補助限定補助流浪犬貓，動保處已針對家犬貓絕育補助，向行政院農業委員會申請3,500隻犬貓三合一下鄉絕育計畫獲准，未來將排定至沿海及本市離動物醫院較偏遠之地區辦理犬貓絕育、寵物登記及狂犬病預防注射三合一計畫，待相關工作準備完成後，會將相關排定行程及說明公布於本處網站及發布新聞稿。而如私人收容所犬貓需進行絕育手術，可洽動保處06-2964439，動保處亦可提供相關之協助。動保處表示基於尊重動物生命，對於已剪耳絕育的犬隻不主動捕捉，但對於具攻擊性或是會追吠人車影響安全之犬隻，不論是否剪耳絕育將一律持續進行主動捕捉，並轉做為工作犬或是防疫犬，以維市民的安全。 發稿人：動物防疫保護處動物保護組呂英沖技士 電話：2130958",
    "tags": ""
}