{
    "published": "2017-01-17",
    "title": "「動保不間斷、服務有夠讚」－臺南市動物防疫保護處處長由吳副處長名彬接任",
    "department": "",
    "url": "https:\/\/www.tainan.gov.tw\/News_Content.aspx?n=40854&s=152244",
    "content": "臺南市政府農業局新聞稿臺南市動物防疫保護處處長由本處吳副處長名彬調任，於106年1月17日上午佈達「臺南市動物防疫保護處」新任首長，期許以「動保不間斷、服務有夠讚」向市民宣告。吳名彬處長畢業於國立嘉義大學獸醫系及國立中正大學政治學系政府與公共事務碩士在職專班，公職歷練已24年，曾任職於臺中縣家畜疾病防治所技佐、臺北縣衛生局獸醫師，84年調回故鄉，在臺南縣家畜疾病防治所擔任技佐、技士、課長、技正等職，時間長達15年，及1年之農業局科長，5年之動保處副處長職，熟稔動物防疫、保護相關業務，今年1月16日獲調升動物防疫保護處處長。新任吳處長一路從基層做起，於96年榮獲中華民國獸醫師公會全國聯合會頒「傑出貢獻獎」及104年榮獲本市及行政院模範公務人員，學經歷俱佳，勇於任事，心繫職務認真負責，為千頭萬緒的動物防疫、保護業務注入心力，工作表現獲各級長官及產業界肯定。農業局局長許漢卿表示，秉持市長「用人唯才，適才適所」的原則，吳處長接掌新職務乃適得其所，相信必能發揮所長，提升服務品質，全力推動動物防疫保護重大政策。（聯絡人：農業局人事室科員陳加綺電話：06-6322231轉6586）",
    "tags": ""
}