{
    "published": "2014-05-23",
    "title": "市議員陳秋萍、郭國文、郭清華總質詢  市府回應20路、19路公車、抑制房市炒風及關切老人照護等議題",
    "department": "",
    "url": "https:\/\/www.tainan.gov.tw\/News_Content.aspx?n=40853&s=174294",
    "content": "（永華市政中心發布）台南市議會第一屆第七次定期大會今（23）日由市議員進行陳秋萍、郭國文、郭清華進行市政總質詢。市府針對20路公車路線變更、19路電動公車通車、健全房市及老人照護等議題說明如下：陳秋萍議員憂心19路電動公車（安平—大灣）進度。交通局長張政源表示，市府對於臺南市第一條電動公車路線的運輸計畫，期許很高；但得標廠商高雄客運公司因製造商交車問題，經過幾個月的折衝，製造電動公車廠商還是無法如期交車，目前已解約。至於補助款問題，經過市府積極與交通部溝通及爭取，日前已獲交通部同意保留4660萬補助款，再另行辦理招商，如順利可望今年底完成通車。另針對20路公車變更行駛路線，張局長指出，配合今年南紡夢時代開幕，20路公車將會延駛到南紡夢時代，至於延駛至火車站的建議，因牽涉到公車路網的整體規劃，市府會再研議考量。郭國文議員關切臺南房市問題。賴市長指出，一般認為房價飆升是由於中央稅制政策，降稅後熱錢無處可去而投入房地產，現在社會討論是要如何壓制房價，但他認為是要如何的引導，以增加溪北地區發展的機會。賴市長說他曾與建築投資公會座談，邀請他們為臺南市未來的發展做三件事情：第一、在溪北投資建案。第二、為年輕人首次購屋族設計符合他們需求的房子。第三、為在他鄉奮鬥退休返鄉的臺南人設計他們所需要的房子。賴市長表示，他希望將臺南市發展的力量引導到溪北，讓臺南市平衡發展，市府會將基礎建設做好，包括解決淹水問題、建構公車系統、道路開闢、工業區開發等，提升生活機能。再者市府土地釋出會考慮區域平衡，運用重要建設計劃，配合土地釋出的手段，來推動溪北地區發展，相信這幾年市府在溪北的建設，成效一定會慢慢的展現出來。另外，關於容積獎勵政策，除了配合中央政策外，市府也在台南市低碳城市自治條例中納入獎勵綠建築、太陽能等相關規範，以九份子低碳社區為例，就是第一個運用此精神的示範區，以逐步推動台南市低碳城市願景。郭清華議員關切老人照顧問題，盼減輕年輕人的經濟壓力。賴市長表示，臺南市總人口有188萬多人，65歲以上有22萬多人，約占總人口數12.6％，較臺灣平均值為高，所以照護老人是市府重要的施政課題；目前市府對老人的照護有三大方向：第一、健康促進；第二、尊嚴自主；第三、社會參與。賴市長認為公部門資源有限，市府推動公私協力，善用民間資源，臺南市是一個非常有愛心的城市，如縣市合併升格前，全市復康巴士僅有30輛，目前已超過100輛，這些完全都是社會主動捐輸，對此也要感謝社會各界對市府公益政策長期的支持。",
    "tags": ""
}