{
    "published": "2015-09-25",
    "title": "每週六防疫清潔日   全民防疫無假期",
    "department": "",
    "url": "https:\/\/www.tainan.gov.tw\/News_Content.aspx?n=40854&s=145843",
    "content": "中秋連假適逢週六防疫清潔日，全民防疫無假期，臺南市政府環保局強調，杜絕登革熱，防疫工作不懈怠，除動員各單位持續加強清除孳生源，不容許積水容器及髒亂點產生，也會加強清運家戶垃圾。投藥、噴藥滅蚊工作不中斷，籲請市民朋友歡度佳節不忘防疫，確實檢查家戶內外環境，清除積水容器，維護環境整潔，讓病媒蚊無法孳生，早日讓疫情降溫。環保局表示，市府自本(9)月起訂每週六為防疫清潔日，已動員市府各單位及環保志義工投入防疫工作，加強清除積水容器及髒亂點。登革熱疫情嚴峻，除充分配合防疫工作，整理居家內外環境外，再次呼籲市民朋友，中秋佳節如有相關活動，請避開上午9時至11時、下午3時至5時病媒蚊喜好的活動時間，可利用這段時間進行室內外的孳清工作，確實檢查家戶內外環境，徹底清除積水容器，活動時間請穿著淺色長袖衣物、噴防蚊液等防護，做好避免被叮咬的措施，平安健康過中秋。環保局表示，市府配合中央流行疫情指揮中心在中秋節前夕執行清除孳生源專案計畫，並於中秋節前一天擴大辦理防疫清潔日，全面動員協同市民巡查清除屋後溝、屋頂盆栽、地下室積水、屋簷排水設施，做好巡、倒、清、刷工作，確保防疫工作滴水不漏，根絕病媒蚊孳生源。環保局同時加強稽巡查，發現孳生病媒蚊的積水容器立即開罰，裁處3,000元以上6,000元以下罰鍰。\n承辦單位：清淨家園管理科 承辦人：陳柏均 電話：2086630#525",
    "tags": ""
}