{
    "published": "2015-09-01",
    "title": "臺南文旦大賽，參賽果品安全過關",
    "department": "",
    "url": "https:\/\/www.tainan.gov.tw\/News_Content.aspx?n=40854&s=150788",
    "content": "2015年台南文旦大賽，74件參賽果品，農藥殘留檢測全部樣品均合格，即將在9月3日於民治市政中心南瀛堂辦理果品評鑑。\n參加2015年台南市文旦大賽原先報名計有86名，由於八月間受到蘇迪勒颱風來襲受損，為利農民清園，取消第一階段果園評鑑。農業局徵詢報名參賽者意見，仍有74名願繼續參與第二階段果品評鑑；遂於8月18日由採果人員赴各參賽者果園進行採果封箱後集中貯放，並抽樣送臺南市衛生局進行檢驗，經該局依多重殘留分析方法（五）及殺菌劑二硫代胺基甲酸鹽類之檢驗（二）進行310項農藥殘留檢測，74件樣品全數合格。\n農業局表示，參賽者之果品，將於9月3日上午8時起在民治市政中心南瀛堂邀請專家，就果形外觀、果肉糖度、肉質風味、種子數等項目進行果品評鑑，並於當日公佈得獎名單。\n\n發稿單位：臺南市政府農業局發稿日期：104年9月1日聯絡人：楊復森技士聯絡電話：06-6328755",
    "tags": ""
}