{
    "published": "2012-04-10",
    "title": "義消特搜隊訓練",
    "department": "",
    "url": "https:\/\/www.tainan.gov.tw\/News_Content.aspx?n=40854&s=50189",
    "content": "臺南市政府消防局為增進義消特搜中隊城市搜救能力，特辦理倒塌建築物震災搜救訓練，以及對於重大災害事故發生時，動員運作機制與應變情形，特定於3月22、23日及4月9，10日分二階段，移師竹山內政部消防署訓練中心，辦理為期四天的密集訓練，以利執行相關災害搶救及運作。 臺南市政府消防局局長李明峯特別驅車前往竹山訓練中心慰問特搜隊訓練的辛勞，並頒發3000元加菜金。消防局局長李明峯表示，義消特搜中隊為強化震災搜索搶救能力，特別請求能至消防署竹山訓練中接受為期4日之城市搜救訓練 ，該中隊並自行委請消防署特種搜救隊南部分隊人員擔任本次訓練師資，訓練項目包括人命搜索作業、傷患救出及搬運、倒塌建築物支撐作業、重物般移及侷限空間救援、倒塌建物障礙破壞作業及震災救援各項作業。期望本次訓練能增進義消特搜隊成員面對各項災害時應有的觀念及處置，以期日後面對各項複合型災難，尤其是城市型，可在黃金救援時間內發揮最大戰力，保障社會大眾生命財產安全。",
    "tags": ""
}