{
    "published": "2016-05-19",
    "title": "2015520情定南戶－愛你一路我愛你，框住幸福迎新人",
    "department": "",
    "url": "https:\/\/www.tainan.gov.tw\/News_Content.aspx?n=40854&s=158695",
    "content": "520諧音「我愛你」，每年都是結婚登記好日子，今年2016年的520，又有「愛你一路我愛你」涵意。\n為符合新人期待，南區戶政創意團隊，每年推陳出新，交出多項全國首創新人服務，並於去年獲得「第七屆政府服務品質獎」評審高度肯定。\n迎接今年520，南戶持續優質新人服務，「愛的禮讚、專人拍照、e定幸福、伴手有禮」等四步驟，打造＂結婚四步曲＂客製化流程，並提供＂咱府城ㄟ傳統禮俗＂，也準備金鏟子－祝你好孕，方便每對新人體驗古早味的府城嫁娶禮俗。\n南區戶政江學通主任表示，為表示全體同仁致賀誠意，520全日特別加碼「幸福立可拍」及「框住幸福、為愛按讚」活動，由同仁親自一刀一刻，將珍貴照片嵌入本所用心設計的「情定南戶520」紀念相框，並親筆落款簽名，讓南區戶政百分百的祝福誠意，直達新人心底。",
    "tags": ""
}