{
    "published": "2016-05-23",
    "title": "回應李文正議員「根據101普通高級中學課程綱要所編之歷史課本偽造歷史」",
    "department": "",
    "url": "https:\/\/www.tainan.gov.tw\/News_Content.aspx?n=40854&s=1311503",
    "content": "臺南市政府教育局表示，賴市長已於103年1月29日第146次市政會議及228追思紀念會宣示：｢本市所轄的四所市立高中一律採用100年版課綱審查之教科書。｣且104年本市四所市立高中即採用100年版課綱審查之教科書。主要是對於本次教育部修改高中歷史課綱完全背離對台灣歷史認同及台灣主體性的認知，絕對不被台灣社會主流價值所接受，同時四所市立學校對100年版課綱及教育部微調課綱差異部分，也編列相關補充教材，做為學校教師教學參考之用。 至於李文正議員提及「普通高級中學課程綱要」歷史科綱要 （101課綱）指稱開羅宣言把臺灣交給中華民國偽造歷史，在市面上蒐羅到南一、龍騰、三民等版本說明皆是如此。教育局表示，對於議員所提意見予以尊重，並已請國教輔導團彙整市面上相關版本內容及相關歷史文獻將針對課本陳述及教學指引部分，提供專業授課建議方向，於2個月內編列補充教材，提供學校教師教學參考，不影響學生學習權益。發稿單位：臺南市政府教育局業務聯繫人：課程發展科黃哲彬 電話：2991111#1530新聞聯繫人：新聞秘書吳幸樺 電話：2991111#8333",
    "tags": ""
}