{
    "published": "2016-05-03",
    "title": "優先保護聚落安全 賴市長視察後壁區菁寮排水整治成效",
    "department": "",
    "url": "https:\/\/www.tainan.gov.tw\/News_Content.aspx?n=40853&s=173250",
    "content": "(民治市政中心發佈)為提升後壁地區防洪排水功能，市府辦理菁寮排水治理應急工程，今（3）日台南市長賴清德偕同水利局長李孟諺前往現場視察後表示，市府聽取地方各界的意見來執行各項工程，在有限經費下，編列預算分段治理菁寮排水。現階段水利局依地形、地物提出村落圍堤方案，以保護民眾生命安全為首要任務，未來市府將持續爭取中央補助，逐步完成菁寮排水全線治理工程。多年來，後壁地區常是颱風或豪大雨肆虐的重災區，為解決該區淹水問題，市府迄今總共投注約5億3千多萬元，用於治理菁寮排水系統（含主、支流），施作項目包括菁長橋上游段護岸應急工程、菁寮抽水站、村落圍堤水門、景觀公園，以及後續的新嘉橋改建工程、滯洪池及護岸治理等工程。依據水利局長李孟諺簡報表示，菁寮排水系統（含支線）長達29.53公里，其上、下游處於省政府時期已整治完成，尚餘中游段人口密集處約8公里未施作堤防，若要通盤整治完工，初估約需15億，且恐耗時30年；在款項無法一次到位的情況下，市府決定優先施作菁寮排水菁長橋上游段左岸護岸，以保護人口聚集的頂長、平安里為首要目標。該工程在去(104)年杜鵑颱風的來襲下，發揮良好效果，確保頂長、平安里人口聚落區無淹水情況。李局長進一步指出，目前左岸護岸工程1、2期已完成，第3期施工進度達9成，第4期亦於今(105)年4月12日決標，預計年底完工，屆時將完成總長1.58公里的護岸改善工程。本案4期投入經費總計1.25億元，改善後的護岸高4.8公尺、河道寬30公尺，可有效改善洪水氾濫情形，提升民眾居住安全。目前菁寮排水系統淹水面積大幅減少，且多侷限在農田處，在去年杜鵑颱風之考驗下，平安及頂長里聚落淹水面積已由230公頃縮減為150公頃，顯見菁寮排水護岸應急工程的成效。然治水腳步不能稍歇，在完成菁寮排水上游段聚落保護後，水利局將持續向中央爭取106、107年綜合流域治理計畫，辦理「後壁區菁寮排水臺糖鐵道橋上游護岸治理工程」、「菁寮排水新嘉橋改建工程（南82線）」及「菁寮排水新嘉橋上下游護岸治理工程」，共計經費2.76億（目前辦理用地徵收中），逐一完成菁寮排水整治。",
    "tags": ""
}