{
    "published": "2015-11-02",
    "title": "古井庭園荒廢20年  環境改造陋巷現生機",
    "department": "",
    "url": "https:\/\/www.tainan.gov.tw\/News_Content.aspx?n=40854&s=145026",
    "content": "臺南市新化區清水社區一處近百坪的農舍庭園荒廢20年，水塘淤塞，雜草齊屋，蛇鼠聚集。臺南市政府環保局輔導清水社區發展協會提出社區環境改造計畫，獲得環保署經費補助，社區環保義工齊力整理空地闢為菜園、花圃，打通前後通道，整理漥地注入活水、保存古井，讓陋巷重現生機。清水社區發展協會理事長盧勝一說，這處農舍是林家五兄弟共有，但均已遷居他處。其中一個所有人林文凱是社區環保義工隊的成員，經由他的協助，歷經一年協商，終於取得其他四兄弟同意，完成認養手續。林文凱說，加入環保義工隊就是要為社區服務，讓環境變好。社區要認養老家，「當然樂見其成」。他不僅協助社區完成認養手續，還參與改造工作，現在早晚都來澆水除草，維護改造成果。他強調，「這裡畢竟是我的家」，能把廢墟變綠地，當然要持續維護。環保署今年3月核准清水社區環境改造計畫，經過近半年的努力，社區環保義工化腐朽為神奇，將滿地瓦礫雜草的髒亂點變成花園、菜圃，重闢水塘回收地下水，保留古井加蓋草寮，搭配入口處設置「倚牆物語」介紹環境改造過程，並以地主兄弟名字取名「根文園」，增添在地人文氣息，塑造都市叢林中的一處古井農園，陋巷重現生機。\n提供單位：綜合規劃科承辦科長：陳賜章06-2686751#320承辦人 ：邱佩璿06-2686751#321",
    "tags": ""
}