{
    "published": "2014-11-08",
    "title": "「2014南瀛獎頒獎典禮」藝氣風發展南瀛 賴市長期勉再接再厲 朝國際化邁進",
    "department": "",
    "url": "https:\/\/www.tainan.gov.tw\/News_Content.aspx?n=40853&s=167160",
    "content": "（永華市政中心發布）南瀛藝文盛事2014南瀛獎頒獎典禮今（8）日於新營文化中心盛大舉行，由市長賴清德親自頒獎表揚首獎及南瀛獎得主。賴市長期勉南瀛獎再接再厲，未來可逐漸朝國際化的發展方向邁進，成為台南市美術館典藏蒐羅全國及世界優秀作品的先鋒部隊。賴市長表示，「南瀛獎」已經有20幾年的歷史，從過去台南縣政府時代就已經開始，締造了良好的名聲及基礎，所以縣市合併升格之後仍繼續辦理。希望大台南能藉由南瀛獎廣徵全台灣各界藝術同好及傑出藝術工作者，能夠參與台南南瀛獎活動，也藉此彰顯大台南以文化藝術立市的精神。賴市長感謝來自全國各地優秀的藝術參賽者的共襄盛舉，今年計有689位參賽者，提供作品高達2067件。經過全國各類著名藝術家及學者所組成的評審團，歷經嚴格的初審、複審、決審三階段，終於精選出2014南瀛獎得主3位、首獎4位、優選13位、佳作18位、入選48位，得獎者共計86位。賴市長相信每一位得獎者未來在文化藝術上的表現，一定非同凡響。賴市長進一步指出，文化藝術之都-台南能在升格直轄市後的4年內有這麼精彩的蛻變，這與市府文化局的執行力密切相關。展望未來，在文化建設方面，賴市長希望達到「一二三四五」的目標，包括：強化一間全新的總圖書館、整建兩座演藝廳（新化演藝廳、新營文化中心演藝廳）、射出文資保存三支箭（文化資產建材銀行、柳科藝術文物典藏中心、傳統藝術中心）、籌建四座新設文化場館（台南市美術館、台南市歷史博物館、自來水博物館、台江文化中心）、規劃五處主題園區（左鎮菜寮化石園區、水交社文化園區、新化文化園區、新營動漫及傳統產業園區、噍吧哖紀念園區）。賴市長說，未來台南市會有15項新的文化建設，涵蓋的範園相當廣泛，內容也是非常充實。賴市長希望市府能與台南各界、市民朋友共同完成，讓台南市文化藝術之都的地位，能在台灣屹立不搖。一路走來，南瀛獎總共典藏了百餘件精品，拔擢了無數藝術家，也鼓勵了許多有志於藝術道路的年輕人。本屆南瀛獎得主皆以黑馬之姿出線，以專注及創新的創作方式，脫穎而出奪得南瀛獎殊榮。其中參賽作品西方媒材類劉佳琪的「綠光記事(二)」以純熟的水彩技巧表現出寧靜廢墟中波光倒影的光影變化，困在畫面中停泊的小船像徵作者嚮往自由的微妙心境，贏得決審委員的高度讚賞；東方媒材類蔡旻芸的作品「沉･溺」跳脫出傳統水墨既有的框架，以現代水墨抽象技法營造出看似熟悉卻又不真實的三合院場景，以個體間疏離的距離，探討現代人與人相處的假象；書法篆刻類林滄池以篆刻作品「作青山明月主人」以刀為筆以石為紙，在主要作品及2件參考作品中，帶來高達57顆形式完整的印石，方寸之中行刀如筆，將書法技法靈活運用於篆刻刀鋒，刀法流暢活潑深具有藝術性，以上三件作品在眾多作品之中脫穎而出勇奪南瀛獎最高殊榮。本屆南瀛獎得獎作品及評審委員邀請展於103年11月1日至30日假新營文化中心第一、二、三畫廊及文物陳列室展出，歡迎有興趣的市民朋友，一同參與這南瀛藝壇的年度盛事。",
    "tags": ""
}