{
    "published": "2011-12-02",
    "title": "打造學童夢想圖書館 啟動閱讀希望工程",
    "department": "",
    "url": "https:\/\/www.tainan.gov.tw\/News_Content.aspx?n=40854&s=152497",
    "content": "玉山金控與玉山志工基金會捐贈本市新市區大社國小「玉山圖書館」，並於100年12月2日舉行落成啟用典禮，由校長李清輝代表受贈，全校師生、家長、社區人士歡喜同賀，感恩迎接。\n 大社國小位處鄉村，家庭弱勢學童約為全校的25％，文化刺激不足，但行政團隊在賴市長推動書香大臺南的教育政策號召下，有明確的閱讀推動藍圖，教師們積極參與，家長主動成立義工組織，協助學校推動閱讀教育活動，是一所努力為孩子打造優質閱讀環境的學校。9月中旬經玉山志工到校訪視評估後，決定捐贈大社國小第45座「玉山圖書館」。\n 工程歷經一個半月，「玉山圖書館-hope 45」於100年12月2日下午3時正式落成啟用。當日由教育局副局長黃緒信、玉山金控總經理黃男州以及校長李清輝共同為圖書館的落成啟用剪綵揭幕，參與的師生、家長們無不以歡喜、感恩的心迎接這座孩子夢想的圖書館。大社國小亦準備了直笛隊與本土語言小天使參與演出，各展才華，一起慶祝這美好時刻的到來。\n 「玉山圖書館」落成啟用後，校方表示，這座充滿童趣與想像的圖書館，可以激發師生教與學更多元、創意的思維，除校內教學運用外，寒暑假期將開放供社區民眾使用，以發揮圖書館最大效益，營造社區書香文化。\n 教育局局長鄭邦鎮指出，閱讀教育與家庭、學校與社會風氣都有關，臺南市未來會繼續透過各種途徑，培養孩子自發性熱愛閱讀、喜歡看書的習慣，在質與量上都會有明顯的提升。因此希望透過玉山銀行捐贈本市國小圖書館義行，能發揮拋磚引玉效果，吸引更多民間資源挹注，共同為孩子裝上飛向夢想的翅膀。\n\n\n\n\n\n發稿單位：臺南市政府教育局國小教育科\n撰稿人：黃慶圓小姐\n聯絡電話：（06）3901310",
    "tags": ""
}