{
    "published": "2011-12-28",
    "title": "臺南市公有路外停車場優惠月票原價1折起大促銷",
    "department": "",
    "url": "https:\/\/www.tainan.gov.tw\/News_Content.aspx?n=40854&s=140563",
    "content": "臺南市政府交通局為提昇臺南市公有收費路外停車場之整體使用效益及改善當地交通狀況，自101年1月1日至101年12月31日止試辦17處臺南市公有停車場優惠月票方案（詳附件），最便宜月票低於原售價金額（3200元）之1折，最貴月票亦不高於原售價金額之7折；路外停車場月票由臺南市政府交通局公有停車場管理中心發售（公11及公6停車場月票於其繳費櫃檯亦有販售），請民眾踴躍購買。臺南市政府交通局表示，臺南市部分公有路外停車場納入收費迄今，停車使用率偏低，為鼓勵民眾使用路外停車場及兼顧使用者付費原則，進行檢討各路外停車場，實施促銷月票方式吸引民眾使用，以有效提昇路邊停車周轉率及改善交通秩序。臺南市政府交通局說明，月票卡以月份為單位申購，辦理日期為每月15日至月底申購次一月份之月票，各停車場月票卡每月發售總數以其停車格位數為上限張數，依序發售，售完為止；這項促銷月票方案將自101年1月1日至101年12月31日止，並於期限屆滿前，視停車場停車狀況重新檢討促銷方案。發稿人：臺南市政府交通局陳科彰電話：(06)390-1326",
    "tags": ""
}