{
    "published": "2013-11-30",
    "title": "台南市國際移民日嘉年華 各國新移民聚集同歡",
    "department": "",
    "url": "https:\/\/www.tainan.gov.tw\/News_Content.aspx?n=40853&s=175689",
    "content": "（永華市政中心發佈）每年12月18日是聯合國制訂定的「國際移民日」，台南市政府、內政部移民署等單位合辦的「國際移民日嘉年華」活動，30日下午在台南遠東百貨前廣場登場，吸引不少來自越南、印尼、中國等地的新住民前往參加。台南市長賴清德除肯定新住民積極融入台灣社會的努力，也頒發「模範新市民」獎狀給在各領域表現傑出的新移民。由於活動適逢假日，不少新移民家庭都穿上故鄉的傳統服裝呼朋引伴前來參加，現場也提供各國美食攤位供闖關成功者品嚐，氣氛相當熱鬧。移民署副署長張琪、市議員洪玉鳳、林美燕、勞工局長王鑫基、教育局副局長黃緒信等貴賓均前來參加。賴市長指出，台南市社會各界非常關心與歡迎新住民朋友在這個城市共同努力、共同發展。台南市的新住民人數很多，貢獻也很大，彼此關係密切。台南市的小學生中新住民約佔百分之十，市府教育局、勞工局均非常關心新住民的生活情況，台南市也獲選為推動101學年度全國新住民火炬計畫績優城市，希望新住民能把這裡當作自己的家。活動中賴市長也特別介紹幾位表現優秀的新住民，如來自越南的阮青河小姐原本擔任女工，在台灣結婚生子後還一面進修，目前在成大歷史系攻讀博士。而去年移民署舉辦的「新住民親子母語歌謠競賽」中，蘇依英小姐與兩位子女獲得印尼語組全國第二名，童氏容小姐與子女得到越南語組全國第二名，賴市長強調，這證明新住民來到台南生活的很愉快，希望大家未來把台灣的經濟力量延伸到越南、泰國等地後，帶著子女一起光榮返鄉。(新聞發佈：新聞及國際關係處吳蕙芬3901490、攝影：蘇英豪)",
    "tags": ""
}