{
    "published": "2017-07-29",
    "title": "尼莎颱風搗亂，南區「臺灣囝仔暑期夏令營」課程縮為1天",
    "department": "",
    "url": "https:\/\/www.tainan.gov.tw\/News_Content.aspx?n=40854&s=135665",
    "content": "由南區區公所主辦、南臺科技大學基層文化服務社承辦的「2017臺灣囝仔暑期夏令營」活動，在今(29)日在灣裡省躬國小登場；惟考量尼莎颱風來襲，原訂兩天活動縮減為一天，30日活動因安全理由決定取消。\n  本年始業式選在灣裡聯合里活動中心舉辦，由南區區長朱棟偕同當地民意代表、里長及校長等貴賓共同主持。南區區長朱棟表示，臺灣囝仔暑期夏令營已在南區舉辦多年，主要招收設籍本區的國小學童，是南區相當受歡迎的暑期重要活動，今年更是開放首日上午立即額滿，其中不乏許多家長替家中孩童連續報名多年，當確認報名成功後展露出喜悅的表情，顯見往年辦理的成效良好，讓家長們願意持續支持臺灣囝仔夏令營活動。  本次營隊恰好遭遇尼莎颱風來搗亂，外圍環流影響造成天候不穩定，但南大科大志工學生與夏令營小朋友們的熱情卻不被風雨給澆熄，仍以最活潑快樂的心情一起為夏令營揭開序幕。南區區公所表示，在氣象預報及天候狀況的綜合評估之下，為了顧及學生志工以及參加孩童之安全性，決定夏令營活動由原定2日縮減為今天1日。雖然時間縮減，但小朋友喜愛的晚會活動及結業式仍照常辦理，希望在颱風尚未影響之際，給予小朋友難忘的夏令營體驗。",
    "tags": ""
}