{
    "published": "2011-07-29",
    "title": "2011台南愛文芒果成果說明會及企業認購記者會",
    "department": "",
    "url": "https:\/\/www.tainan.gov.tw\/News_Content.aspx?n=40853&s=175650",
    "content": "已進入產期尾聲的臺南愛文芒果，今(29)日上午由臺南市農業局，特舉辦「成果說明暨企業認購記者會」，為今年產季最後一波美味，推出限量團體認購活動，也鼓勵各大企業團體，明年度可提早預購愛文芒果，並藉此機會宣布，今年度愛文芒果的行銷成績。賴清德市長以及農糧署蘇茂祥蘇主秘、農業局許漢卿局長、曾王雅雲議員，一同出席本次的記者會。賴市長指出，因去年受到寒害影響，使今年的產量較去年多出了3成，但相較於以往也有2成的增幅，但今年價格穩定，主要是在外銷量與外銷價格上，日本、中國、韓國都是成長的，因此保障了果農基本的收入，不因產量的增加，使芒果價格暴跌，而影響到農民的生計。市長並表示，他十分關心農民的生活，他們總是在大太陽底下，辛苦耕耘，市長一直希望農民的辛苦，能夠得到應有的回報，所以今年為打開行銷通路，特地安排市府團隊，由副市長領軍前往日本銷售、推廣，另一方面也與統一企業集團合作，達成「台灣下單，中日韓均能取貨」的行銷機制。今年臺南市政府，很早就著手進行通路的規劃與建立，因為通路是決定輸贏的關鍵，市長也感謝中華電信訂購了1000箱的愛文芒果，另外還有許多台灣的企業團體也都願意力挺，認購活動相當踴躍，臺南的芒果產期，於8月中之前就會結束，所餘貨量有限，僅約7、8千公斤，想品嘗美味要盡快，得把握最後的機會。農業局長表示，由於本年度愛文芒果的產期較以往延後，因此臺南市大部份的芒果都在七月份開始採收，關於整體產銷工作，在農委會農糧署與臺南市府相關單位共同協力之下完成。於外銷部分，每公斤平均價格都有70元以上的水準，而內銷方面，上星期雖有微幅下滑，但整體平均來說，都還維持在每公斤40元上下的價位，對於辛苦的果農，都維持在成本之上。另外，並啟動芒果加工副產品的補助機制，針對二級果品，製成芒果乾、芒果布丁等，以減少農民的損失，且對價格的穩定有很大的幫助。蘇主秘代表農糧署說明，100年度外銷日本芒果數量達1160公噸，較去年的1537公噸，成長了約百分之十五。今年的芒果大豐收，整體比去年增加3成，主要的原因是農糧署對於芒果這項產業，投入相當多的資源，例如「輸日芒果安全供應體系」的推動，並設置優質供果園，也希望能透過貿易商與優質供果園的農民簽訂合作意願書，讓農民可在技術服務團隊的輔導下，提升技術能力，同時落實品質管控，並加強農藥的檢驗，才使得外銷能有如此豐碩的成果。【新聞聯絡人：新聞及國際關係處  楊小鷞  電話：299-1111  分機：7141】",
    "tags": ""
}