{
    "published": "2011-07-13",
    "title": "南區區公所7月13日召開100年度第1次里長業務聯繫會報",
    "department": "",
    "url": "https:\/\/www.tainan.gov.tw\/News_Content.aspx?n=40854&s=136102",
    "content": "南區區公所依年度計畫召開100年度第1次里長業務聯繫會報，會後併同邀請南區里長餐敘活動，藉由里長業務聯繫活動，宣導市府重要施政理念及加強與基層溝通聯繫，以增進市政團隊、里長及各機關單位彼此之間互動情誼。 里長業務聯繫會報活動於100年7月13日下午16時於南區區公所2樓舉行，會後移至府南里活動中心餐敘。並由全體里長連署向市政府爭取儘速推動「南山公墓遷葬案」，因南山公墓自民國97年3月起即已全面禁葬，長期閒置荒廢，不僅造成鄰近居民生活品質低落，更嚴重影響本區之開發建設，亦冀望市府能重視整體南區之繁榮進步與民眾福祉，儘速進行遷葬開發計畫。 會議前播放「建設新臺南十大旗艦計畫」簡報向里長宣導未來市政擘畫藍圖；衛生局宣導「自殺防治」；社區大學宣導「展愛巡迴服務」本次里長建議案田寮里、府南里、明亮里里長建議巷內水溝年久失修，遇雨即易淹水，經市府及公所經建單位回覆將施作污水埋管工程，為免重復施作，待市府施工後再行研議。郡南里里長建議86號快速道路開通後車流量倍增，影響里民通行安全性，經市府交通單位回覆將永成路三處三色號誌路口設定同步運作，亦持續檢視巷道車流狀況，評估增設號誌管制之必要性。國宅里里長建議新興路500巷口至新建路口L型側溝施作改善，市府公共工程處表示將納入100年度預算計畫辦理改善。 本次會議建議案共計73案，除建檔列管追踪外，並定期向里長回報處理進度。本次會議除函請轄內全體里長、里幹事出席外，並廣邀市府民政、工務、都發、交通、環保、教育、警察等相關單位列席。會中並安排公所各課室作年度施政工作報告，期能使各里長在推動市政上，有更大助益。\n發稿人：南區區公所 課員-黃相忠",
    "tags": ""
}