{
    "published": "2012-03-30",
    "title": "臺南市木棉防制棉絮飛散噴藥說明",
    "department": "",
    "url": "https:\/\/www.tainan.gov.tw\/News_Content.aspx?n=40854&s=153765",
    "content": "台南市木棉花多分布於市區主要幹道兩側，如府前路、東豐路等路段，時至三月開花季節，一朵朵如火焰般開放的橘紅色花朵，每每讓路人及攝影家眼睛為之一亮，尤其陣陣清風拂來，飄落的花朵更讓人驚豔，果實成熟後常在樹上裂開，種子附生有長棉毛隨風四處飄散，偶有難得一見雪國風情。\n惟依據2003年林業研究季刊指出，木棉之棉絮亦可能衍生花粉症，除此之外棉絮飄散將造成住戶紗窗蒙上厚厚棉絮，造成空氣污染及環境髒亂。\n為避免棉絮影響附近居民生活品質，市府於101年3月30日邀請相關里長、專家學者及環保團體討論行道樹修剪方式及落果防制意見，短期參考目前鄰近縣市作為及市府往年作法，以植物生長素噴施木棉花朵，使木棉開花後減少結果，避免棉絮飄散，維持市民居家整潔及周遭環境清潔，亦將於噴灑前告知附近里民及宣導，並請市民及觀光客勿任意觸摸。\n景觀生態與市民生活品質習習相關，在現有環境及人力與經費之考慮下，市府不得不採取部分必要作為，長期將研擬妥善經營管理機制，造就雙贏局面。\n發稿人：林慧雯  聯絡電話：299111#8485",
    "tags": ""
}