{
    "published": "2011-04-15",
    "title": "高齡友善服務啟動！衛生局提供社區功能性體適能檢測！",
    "department": "",
    "url": "https:\/\/www.tainan.gov.tw\/News_Content.aspx?n=40854&s=49735",
    "content": "80歲的林爺爺每天有去公園運動的習慣，某個陰天，因天色未亮、視線不佳，沒發現公園樓梯的雜物而跌倒，導致右大腿骨折。因為害怕再度摔倒，林爺爺的活動範圍就縮小了，也不敢走遠甚至還需要子女攙扶才能下樓梯，像林爺爺這樣的案例，是台灣許多家庭及其家屬共同擔憂的問題。行政院衛生署主計處公布99年底65歲以上台灣長者計有248萬7,893人，占總人口比例達10.74％；台南市65歲以上老人達21萬7,384人占本市人口11.6％，遠高於全國百分比，顯示長者人口快速成長。97年「台灣健康危害行為監測調查」，結果有45.4％最近一次受傷就醫是因跌墜所致，研究指出：老化跌墜與肌力衰退有密切關係，且年長者日常所需的健康體能首重肌力與肌耐力。有鑑於此，臺南市政府衛生局相繼辦理銀髮族體驗課程，讓醫護同仁感同身受長者的世界，以同理心服務民眾，辦理55歲銀髮志工培訓及成立銀髮志工隊，運用社區退休人力，提倡年輕長者服務年老長者的概念。為強化台南市社區關懷據點健康服務，預計4月底進入社區關懷據點提供「老年人功能性體適能檢測」，目的在協助評估長者改善身體機能衰退情形，以生活化、簡易的檢測項目，來判斷其體適能情形，及完成日常生活中所需的身體活動能力。檢測內容包含30秒坐到站、30秒手臂屈舉、2分鐘踏步、椅子坐姿前彎、抓背測驗、落棒測試、八呎立走等項目。台南市政府衛生局提供社區免費檢測，社區可提供70位65歲以上有意願檢測之長者免費檢測，歡迎以社區為單位報名，相關辦法可來電洽詢國民健康科方小姐（06-6357716轉253）、林小姐（06-2677058）。發稿人：國民健康科方秋媛、林家慧連絡電話：06-6357716（東興辦公室）轉253或06-2679751（林森辦公室）轉3413",
    "tags": ""
}