{"22127":"https:\/\/www.tainan.gov.tw\/News_Content.aspx?n=40853&s=22127","30642":"https:\/\/www.tainan.gov.tw\/News_Content.aspx?n=40853&s=30642","31148":"https:\/\/www.tainan.gov.tw\/News_Content.aspx?n=40853&s=31148","32652":"https:\/\/www.tainan.gov.tw\/News_Content.aspx?n=40854&s=32652","49381":"https:\/\/www.tainan.gov.tw\/News_Content.aspx?n=40853&s=49381","50291":"https:\/\/www.tainan.gov.tw\/News_Content.aspx?n=40853&s=50291","50303":"https:\/\/www.tainan.gov.tw\/News_Content.aspx?n=40853&s=50303","50319":"https:\/\/www.tainan.gov.tw\/News_Content.aspx?n=40853&s=50319","50323":"https:\/\/www.tainan.gov.tw\/News_Content.aspx?n=40853&s=50323","50331":"https:\/\/www.tainan.gov.tw\/News_Content.aspx?n=40853&s=50331","50341":"https:\/\/www.tainan.gov.tw\/News_Content.aspx?n=40853&s=50341","52028":"https:\/\/www.tainan.gov.tw\/News_Content.aspx?n=40853&s=52028","131801":"https:\/\/www.tainan.gov.tw\/News_Content.aspx?n=40854&s=131801","133710":"https:\/\/www.tainan.gov.tw\/News_Content.aspx?n=40854&s=133710","148657":"https:\/\/www.tainan.gov.tw\/News_Content.aspx?n=40854&s=148657","158387":"https:\/\/www.tainan.gov.tw\/News_Content.aspx?n=40854&s=158387","162179":"https:\/\/www.tainan.gov.tw\/News_Content.aspx?n=40854&s=162179","170493":"https:\/\/www.tainan.gov.tw\/News_Content.aspx?n=40853&s=170493","172770":"https:\/\/www.tainan.gov.tw\/News_Content.aspx?n=40853&s=172770","176695":"https:\/\/www.tainan.gov.tw\/News_Content.aspx?n=40853&s=176695","176701":"https:\/\/www.tainan.gov.tw\/News_Content.aspx?n=40853&s=176701","176703":"https:\/\/www.tainan.gov.tw\/News_Content.aspx?n=40853&s=176703","176729":"https:\/\/www.tainan.gov.tw\/News_Content.aspx?n=40853&s=176729","176738":"https:\/\/www.tainan.gov.tw\/News_Content.aspx?n=40853&s=176738","176749":"https:\/\/www.tainan.gov.tw\/News_Content.aspx?n=40853&s=176749","176771":"https:\/\/www.tainan.gov.tw\/News_Content.aspx?n=40853&s=176771","176772":"https:\/\/www.tainan.gov.tw\/News_Content.aspx?n=40853&s=176772","176778":"https:\/\/www.tainan.gov.tw\/News_Content.aspx?n=40853&s=176778","176789":"https:\/\/www.tainan.gov.tw\/News_Content.aspx?n=40853&s=176789","176802":"https:\/\/www.tainan.gov.tw\/News_Content.aspx?n=40853&s=176802","176807":"https:\/\/www.tainan.gov.tw\/News_Content.aspx?n=40853&s=176807","176816":"https:\/\/www.tainan.gov.tw\/News_Content.aspx?n=40853&s=176816","176817":"https:\/\/www.tainan.gov.tw\/News_Content.aspx?n=40853&s=176817","176835":"https:\/\/www.tainan.gov.tw\/News_Content.aspx?n=40853&s=176835","187236":"https:\/\/www.tainan.gov.tw\/News_Content.aspx?n=40853&s=187236"}