{
    "published": "2013-01-04",
    "title": "本市善德同憫會捐贈南區明興、明亮里各款低收入戶",
    "department": "",
    "url": "https:\/\/www.tainan.gov.tw\/News_Content.aspx?n=40854&s=138189",
    "content": "本市善德同憫會秉持著關懷在地、回饋社區的精神捐助南區明興、明亮里一、二、三款低收入戶共71戶，每戶白米3公斤一包及民生物資一批。凡收到本所領取通知單之低收入戶者，請於102年01月13日星期日上午10時30分至中午12時止，請攜帶通知單、印章、戶長身分證至臺南市南區金華路一段154巷44號領取，代理領取者請一併攜帶同上證件。 南區公所表示，善德同憫會以實際的行動發放白米及民生物資給有需要的弱勢家庭，對地方熱情奉獻。公所除將結合慈善機構團體與民間資源，鼓勵民間善心人士或企業與積極發揚宗教文化的團體參與社會福利工作以照顧弱勢族群外，並將透過里辦公處及社區發展協會，作好訪視工作、積極辦理扶助弱勢家庭自我發展及社會參與能力之各項活動，宣導弱勢族群新生代正確理財觀念，實現溫暖大臺南的願景。\n發稿人：南區區公所 課員-黃相忠",
    "tags": ""
}