{"12290":"https:\/\/www.tainan.gov.tw\/News_Content.aspx?n=40854&s=12290","22476":"https:\/\/www.tainan.gov.tw\/News_Content.aspx?n=40854&s=22476","53022":"https:\/\/www.tainan.gov.tw\/News_Content.aspx?n=40854&s=53022","53132":"https:\/\/www.tainan.gov.tw\/News_Content.aspx?n=40854&s=53132","53657":"https:\/\/www.tainan.gov.tw\/News_Content.aspx?n=40854&s=53657","55493":"https:\/\/www.tainan.gov.tw\/News_Content.aspx?n=40854&s=55493","131141":"https:\/\/www.tainan.gov.tw\/News_Content.aspx?n=40854&s=131141","131637":"https:\/\/www.tainan.gov.tw\/News_Content.aspx?n=40854&s=131637","131654":"https:\/\/www.tainan.gov.tw\/News_Content.aspx?n=40854&s=131654","132199":"https:\/\/www.tainan.gov.tw\/News_Content.aspx?n=40854&s=132199","132301":"https:\/\/www.tainan.gov.tw\/News_Content.aspx?n=40854&s=132301","132497":"https:\/\/www.tainan.gov.tw\/News_Content.aspx?n=40854&s=132497","132757":"https:\/\/www.tainan.gov.tw\/News_Content.aspx?n=40854&s=132757","134128":"https:\/\/www.tainan.gov.tw\/News_Content.aspx?n=40854&s=134128","134346":"https:\/\/www.tainan.gov.tw\/News_Content.aspx?n=40854&s=134346","135308":"https:\/\/www.tainan.gov.tw\/News_Content.aspx?n=40854&s=135308","135871":"https:\/\/www.tainan.gov.tw\/News_Content.aspx?n=40854&s=135871","136749":"https:\/\/www.tainan.gov.tw\/News_Content.aspx?n=40854&s=136749","137667":"https:\/\/www.tainan.gov.tw\/News_Content.aspx?n=40854&s=137667","138696":"https:\/\/www.tainan.gov.tw\/News_Content.aspx?n=40854&s=138696","140022":"https:\/\/www.tainan.gov.tw\/News_Content.aspx?n=40854&s=140022","140023":"https:\/\/www.tainan.gov.tw\/News_Content.aspx?n=40854&s=140023","140024":"https:\/\/www.tainan.gov.tw\/News_Content.aspx?n=40854&s=140024","141621":"https:\/\/www.tainan.gov.tw\/News_Content.aspx?n=40854&s=141621","142063":"https:\/\/www.tainan.gov.tw\/News_Content.aspx?n=40854&s=142063","142640":"https:\/\/www.tainan.gov.tw\/News_Content.aspx?n=40854&s=142640","143258":"https:\/\/www.tainan.gov.tw\/News_Content.aspx?n=40854&s=143258","143486":"https:\/\/www.tainan.gov.tw\/News_Content.aspx?n=40854&s=143486","146635":"https:\/\/www.tainan.gov.tw\/News_Content.aspx?n=40854&s=146635","148207":"https:\/\/www.tainan.gov.tw\/News_Content.aspx?n=40854&s=148207","152064":"https:\/\/www.tainan.gov.tw\/News_Content.aspx?n=40854&s=152064","152165":"https:\/\/www.tainan.gov.tw\/News_Content.aspx?n=40854&s=152165","153310":"https:\/\/www.tainan.gov.tw\/News_Content.aspx?n=40854&s=153310","153407":"https:\/\/www.tainan.gov.tw\/News_Content.aspx?n=40854&s=153407","154451":"https:\/\/www.tainan.gov.tw\/News_Content.aspx?n=40854&s=154451","155186":"https:\/\/www.tainan.gov.tw\/News_Content.aspx?n=40854&s=155186","158751":"https:\/\/www.tainan.gov.tw\/News_Content.aspx?n=40854&s=158751","160257":"https:\/\/www.tainan.gov.tw\/News_Content.aspx?n=40854&s=160257","168430":"https:\/\/www.tainan.gov.tw\/News_Content.aspx?n=40853&s=168430","169426":"https:\/\/www.tainan.gov.tw\/News_Content.aspx?n=40853&s=169426","170987":"https:\/\/www.tainan.gov.tw\/News_Content.aspx?n=40853&s=170987","171648":"https:\/\/www.tainan.gov.tw\/News_Content.aspx?n=40853&s=171648","172232":"https:\/\/www.tainan.gov.tw\/News_Content.aspx?n=40853&s=172232","175023":"https:\/\/www.tainan.gov.tw\/News_Content.aspx?n=40853&s=175023","176290":"https:\/\/www.tainan.gov.tw\/News_Content.aspx?n=40853&s=176290","608151":"https:\/\/www.tainan.gov.tw\/News_Content.aspx?n=40853&s=608151"}